{
"meta":{"test_sets":[],"test_metrics":[],"learn_metrics":[{"best_value":"Min","name":"MultiClass"}],"launch_mode":"Train","parameters":"","iteration_count":1000,"learn_sets":["learn"],"name":"experiment"},
"iterations":[
{"learn":[1.359759309],"iteration":0,"passed_time":0.1857171271,"remaining_time":185.5314099},
{"learn":[1.342040761],"iteration":1,"passed_time":0.1958441646,"remaining_time":97.72623813},
{"learn":[1.31911407],"iteration":2,"passed_time":0.2053398421,"remaining_time":68.2412742},
{"learn":[1.297504078],"iteration":3,"passed_time":0.2151508769,"remaining_time":53.57256835},
{"learn":[1.281339616],"iteration":4,"passed_time":0.2262025358,"remaining_time":45.01430462},
{"learn":[1.262060714],"iteration":5,"passed_time":0.2367913134,"remaining_time":39.22842758},
{"learn":[1.243869574],"iteration":6,"passed_time":0.2476384268,"remaining_time":35.12927968},
{"learn":[1.225503438],"iteration":7,"passed_time":0.2581653953,"remaining_time":32.01250902},
{"learn":[1.204343033],"iteration":8,"passed_time":0.268155082,"remaining_time":29.52685402},
{"learn":[1.187049461],"iteration":9,"passed_time":0.2782072148,"remaining_time":27.54251427},
{"learn":[1.169008966],"iteration":10,"passed_time":0.2865161023,"remaining_time":25.76040229},
{"learn":[1.155611289],"iteration":11,"passed_time":0.2951235398,"remaining_time":24.29850478},
{"learn":[1.141509882],"iteration":12,"passed_time":0.3053338998,"remaining_time":23.18188916},
{"learn":[1.132198865],"iteration":13,"passed_time":0.3151096528,"remaining_time":22.19272269},
{"learn":[1.117281389],"iteration":14,"passed_time":0.3245437,"remaining_time":21.31170297},
{"learn":[1.105607092],"iteration":15,"passed_time":0.334310232,"remaining_time":20.56007927},
{"learn":[1.090571881],"iteration":16,"passed_time":0.3449616382,"remaining_time":19.94689943},
{"learn":[1.076843057],"iteration":17,"passed_time":0.3544748539,"remaining_time":19.33857259},
{"learn":[1.063980739],"iteration":18,"passed_time":0.3647697473,"remaining_time":18.83363801},
{"learn":[1.052574556],"iteration":19,"passed_time":0.3736162701,"remaining_time":18.30719723},
{"learn":[1.040506316],"iteration":20,"passed_time":0.3833184886,"remaining_time":17.86994288},
{"learn":[1.027167867],"iteration":21,"passed_time":0.3941270159,"remaining_time":17.52073735},
{"learn":[1.01432925],"iteration":22,"passed_time":0.4029783778,"remaining_time":17.11782066},
{"learn":[1.007958333],"iteration":23,"passed_time":0.4133259707,"remaining_time":16.80858947},
{"learn":[1.000843651],"iteration":24,"passed_time":0.4248576069,"remaining_time":16.56944667},
{"learn":[0.9921125826],"iteration":25,"passed_time":0.4362455405,"remaining_time":16.3424291},
{"learn":[0.9831057709],"iteration":26,"passed_time":0.4487607586,"remaining_time":16.17200808},
{"learn":[0.971934035],"iteration":27,"passed_time":0.4599348543,"remaining_time":15.96630994},
{"learn":[0.9615529201],"iteration":28,"passed_time":0.4707089987,"remaining_time":15.76063578},
{"learn":[0.9523868712],"iteration":29,"passed_time":0.4802432387,"remaining_time":15.52786472},
{"learn":[0.9437149616],"iteration":30,"passed_time":0.4893342208,"remaining_time":15.29564064},
{"learn":[0.9349655333],"iteration":31,"passed_time":0.5007675887,"remaining_time":15.14821956},
{"learn":[0.9289250662],"iteration":32,"passed_time":0.5109351834,"remaining_time":14.97194916},
{"learn":[0.9208388214],"iteration":33,"passed_time":0.5234045664,"remaining_time":14.87084739},
{"learn":[0.9111762674],"iteration":34,"passed_time":0.5357654265,"remaining_time":14.77181819},
{"learn":[0.9038266903],"iteration":35,"passed_time":0.5486867813,"remaining_time":14.6926127},
{"learn":[0.8950529512],"iteration":36,"passed_time":0.5604235599,"remaining_time":14.58615914},
{"learn":[0.8897320471],"iteration":37,"passed_time":0.5714731081,"remaining_time":14.46729289},
{"learn":[0.8817359238],"iteration":38,"passed_time":0.5817116445,"remaining_time":14.33397155},
{"learn":[0.8732106605],"iteration":39,"passed_time":0.5918606478,"remaining_time":14.20465555},
{"learn":[0.8648817989],"iteration":40,"passed_time":0.6165318598,"remaining_time":14.42083058},
{"learn":[0.8577224067],"iteration":41,"passed_time":0.6258816114,"remaining_time":14.27606152},
{"learn":[0.8502047714],"iteration":42,"passed_time":0.6368657108,"remaining_time":14.17396477},
{"learn":[0.8428021231],"iteration":43,"passed_time":0.6491488611,"remaining_time":14.10423435},
{"learn":[0.8374076055],"iteration":44,"passed_time":0.6595581614,"remaining_time":13.99728987},
{"learn":[0.8304178115],"iteration":45,"passed_time":0.6693613586,"remaining_time":13.88197253},
{"learn":[0.8256505134],"iteration":46,"passed_time":0.6788535363,"remaining_time":13.76483873},
{"learn":[0.8199375957],"iteration":47,"passed_time":0.6878532353,"remaining_time":13.6424225},
{"learn":[0.813612581],"iteration":48,"passed_time":0.6986914521,"remaining_time":13.56031777},
{"learn":[0.8051535277],"iteration":49,"passed_time":0.7082683192,"remaining_time":13.45709806},
{"learn":[0.7990106114],"iteration":50,"passed_time":0.718645008,"remaining_time":13.37243358},
{"learn":[0.7927290576],"iteration":51,"passed_time":0.7290517701,"remaining_time":13.29117458},
{"learn":[0.7874574605],"iteration":52,"passed_time":0.739695059,"remaining_time":13.21681549},
{"learn":[0.782913039],"iteration":53,"passed_time":0.7509677008,"remaining_time":13.15584157},
{"learn":[0.7783676874],"iteration":54,"passed_time":0.7620650932,"remaining_time":13.09366387},
{"learn":[0.7715258847],"iteration":55,"passed_time":0.7727403663,"remaining_time":13.02619475},
{"learn":[0.7663077741],"iteration":56,"passed_time":0.7843974336,"remaining_time":12.97696105},
{"learn":[0.7569540268],"iteration":57,"passed_time":0.7954544298,"remaining_time":12.91927712},
{"learn":[0.7522588295],"iteration":58,"passed_time":0.8066964985,"remaining_time":12.86612551},
{"learn":[0.7487206386],"iteration":59,"passed_time":0.8177087516,"remaining_time":12.81077044},
{"learn":[0.7438542052],"iteration":60,"passed_time":0.8293818223,"remaining_time":12.76704149},
{"learn":[0.7384025559],"iteration":61,"passed_time":0.8400994384,"remaining_time":12.7098915},
{"learn":[0.732767963],"iteration":62,"passed_time":0.8507696453,"remaining_time":12.65351044},
{"learn":[0.7278978302],"iteration":63,"passed_time":0.8603510181,"remaining_time":12.58263364},
{"learn":[0.7233634951],"iteration":64,"passed_time":0.8711616106,"remaining_time":12.53132471},
{"learn":[0.7171770234],"iteration":65,"passed_time":0.8824956813,"remaining_time":12.48865101},
{"learn":[0.7111472903],"iteration":66,"passed_time":0.891785782,"remaining_time":12.41844977},
{"learn":[0.7058105986],"iteration":67,"passed_time":0.9016415499,"remaining_time":12.35779301},
{"learn":[0.699879169],"iteration":68,"passed_time":0.9118535897,"remaining_time":12.30341583},
{"learn":[0.695723713],"iteration":69,"passed_time":0.9202772126,"remaining_time":12.22654011},
{"learn":[0.6912615668],"iteration":70,"passed_time":0.9297650836,"remaining_time":12.16551778},
{"learn":[0.686981627],"iteration":71,"passed_time":0.9403861887,"remaining_time":12.1205331},
{"learn":[0.6823616801],"iteration":72,"passed_time":0.952155604,"remaining_time":12.09107185},
{"learn":[0.6785100422],"iteration":73,"passed_time":0.963676845,"remaining_time":12.05898322},
{"learn":[0.6739810115],"iteration":74,"passed_time":0.9758408512,"remaining_time":12.0353705},
{"learn":[0.670542701],"iteration":75,"passed_time":0.987807643,"remaining_time":12.00966134},
{"learn":[0.6675176558],"iteration":76,"passed_time":0.9978049798,"remaining_time":11.96070125},
{"learn":[0.6626839404],"iteration":77,"passed_time":1.009313036,"remaining_time":11.93059768},
{"learn":[0.6591441535],"iteration":78,"passed_time":1.021222856,"remaining_time":11.90564874},
{"learn":[0.656420781],"iteration":79,"passed_time":1.031539031,"remaining_time":11.86269886},
{"learn":[0.651469499],"iteration":80,"passed_time":1.043056284,"remaining_time":11.83418179},
{"learn":[0.6474821689],"iteration":81,"passed_time":1.055225084,"remaining_time":11.81337351},
{"learn":[0.6427814258],"iteration":82,"passed_time":1.066118511,"remaining_time":11.77868283},
{"learn":[0.6386900397],"iteration":83,"passed_time":1.077296739,"remaining_time":11.74766444},
{"learn":[0.6340069799],"iteration":84,"passed_time":1.087823952,"remaining_time":11.7101049},
{"learn":[0.6300506337],"iteration":85,"passed_time":1.097738153,"remaining_time":11.66665897},
{"learn":[0.6254188047],"iteration":86,"passed_time":1.10719209,"remaining_time":11.61915377},
{"learn":[0.6216134916],"iteration":87,"passed_time":1.117204011,"remaining_time":11.57829612},
{"learn":[0.6178113488],"iteration":88,"passed_time":1.12925432,"remaining_time":11.55899647},
{"learn":[0.6126163628],"iteration":89,"passed_time":1.14010981,"remaining_time":11.52777697},
{"learn":[0.6091709948],"iteration":90,"passed_time":1.151892976,"remaining_time":11.50627159},
{"learn":[0.6058225135],"iteration":91,"passed_time":1.162433768,"remaining_time":11.47271588},
{"learn":[0.6014842668],"iteration":92,"passed_time":1.174700459,"remaining_time":11.45648727},
{"learn":[0.5982323317],"iteration":93,"passed_time":1.185722444,"remaining_time":11.42834611},
{"learn":[0.5950250575],"iteration":94,"passed_time":1.197614724,"remaining_time":11.40885606},
{"learn":[0.590335551],"iteration":95,"passed_time":1.209914541,"remaining_time":11.39336193},
{"learn":[0.5863779819],"iteration":96,"passed_time":1.222322143,"remaining_time":11.37893707},
{"learn":[0.5837536494],"iteration":97,"passed_time":1.233269207,"remaining_time":11.35111046},
{"learn":[0.5805881068],"iteration":98,"passed_time":1.244941125,"remaining_time":11.33022175},
{"learn":[0.5781231944],"iteration":99,"passed_time":1.25656792,"remaining_time":11.30911128},
{"learn":[0.5734326483],"iteration":100,"passed_time":1.268590015,"remaining_time":11.29170716},
{"learn":[0.5690743385],"iteration":101,"passed_time":1.280942415,"remaining_time":11.27731655},
{"learn":[0.566957944],"iteration":102,"passed_time":1.292957786,"remaining_time":11.26003042},
{"learn":[0.5635531474],"iteration":103,"passed_time":1.305141324,"remaining_time":11.24429448},
{"learn":[0.5608374599],"iteration":104,"passed_time":1.315983904,"remaining_time":11.21719614},
{"learn":[0.5577060057],"iteration":105,"passed_time":1.327147339,"remaining_time":11.19311058},
{"learn":[0.5540770843],"iteration":106,"passed_time":1.339185374,"remaining_time":11.17656579},
{"learn":[0.5512970171],"iteration":107,"passed_time":1.352404049,"remaining_time":11.16985566},
{"learn":[0.5492951252],"iteration":108,"passed_time":1.365348029,"remaining_time":11.16078067},
{"learn":[0.5450839071],"iteration":109,"passed_time":1.377822971,"remaining_time":11.1478404},
{"learn":[0.5428477575],"iteration":110,"passed_time":1.390465228,"remaining_time":11.13624854},
{"learn":[0.5405804552],"iteration":111,"passed_time":1.40526584,"remaining_time":11.14175059},
{"learn":[0.5371343636],"iteration":112,"passed_time":1.418706888,"remaining_time":11.13622132},
{"learn":[0.5341626242],"iteration":113,"passed_time":1.431038662,"remaining_time":11.12193206},
{"learn":[0.531701696],"iteration":114,"passed_time":1.443283164,"remaining_time":11.10700522},
{"learn":[0.529907135],"iteration":115,"passed_time":1.457039993,"remaining_time":11.10364961},
{"learn":[0.5269632277],"iteration":116,"passed_time":1.469365859,"remaining_time":11.0893167},
{"learn":[0.5231317888],"iteration":117,"passed_time":1.482327705,"remaining_time":11.07977149},
{"learn":[0.5206094915],"iteration":118,"passed_time":1.493313041,"remaining_time":11.05553605},
{"learn":[0.5188124103],"iteration":119,"passed_time":1.504972259,"remaining_time":11.03646323},
{"learn":[0.5165666494],"iteration":120,"passed_time":1.516477474,"remaining_time":11.01639421},
{"learn":[0.5133349226],"iteration":121,"passed_time":1.528621296,"remaining_time":11.00106146},
{"learn":[0.511175968],"iteration":122,"passed_time":1.540276174,"remaining_time":10.98229434},
{"learn":[0.5098278718],"iteration":123,"passed_time":1.552300547,"remaining_time":10.96625225},
{"learn":[0.5076858694],"iteration":124,"passed_time":1.56380869,"remaining_time":10.94666083},
{"learn":[0.5049160932],"iteration":125,"passed_time":1.576029872,"remaining_time":10.93214372},
{"learn":[0.5015088556],"iteration":126,"passed_time":1.587657165,"remaining_time":10.91358035},
{"learn":[0.4992456414],"iteration":127,"passed_time":1.599668846,"remaining_time":10.89774402},
{"learn":[0.4958450247],"iteration":128,"passed_time":1.612638164,"remaining_time":10.88843287},
{"learn":[0.4931402841],"iteration":129,"passed_time":1.624110141,"remaining_time":10.86904479},
{"learn":[0.4910349339],"iteration":130,"passed_time":1.636130688,"remaining_time":10.85341655},
{"learn":[0.4881147065],"iteration":131,"passed_time":1.646850449,"remaining_time":10.82928932},
{"learn":[0.4848087856],"iteration":132,"passed_time":1.658369682,"remaining_time":10.81057529},
{"learn":[0.482900079],"iteration":133,"passed_time":1.669574769,"remaining_time":10.78993844},
{"learn":[0.4800427869],"iteration":134,"passed_time":1.680348369,"remaining_time":10.76667659},
{"learn":[0.4763988405],"iteration":135,"passed_time":1.692282086,"remaining_time":10.75096855},
{"learn":[0.4727897406],"iteration":136,"passed_time":1.702919989,"remaining_time":10.72715292},
{"learn":[0.4712429061],"iteration":137,"passed_time":1.714497554,"remaining_time":10.70939776},
{"learn":[0.4693501115],"iteration":138,"passed_time":1.726656115,"remaining_time":10.69533033},
{"learn":[0.4662400055],"iteration":139,"passed_time":1.738608102,"remaining_time":10.6800212},
{"learn":[0.4640017939],"iteration":140,"passed_time":1.750641827,"remaining_time":10.66525765},
{"learn":[0.4614819903],"iteration":141,"passed_time":1.763045505,"remaining_time":10.65276791},
{"learn":[0.4586509621],"iteration":142,"passed_time":1.774684517,"remaining_time":10.63569672},
{"learn":[0.4567298013],"iteration":143,"passed_time":1.786043014,"remaining_time":10.61703347},
{"learn":[0.4543699212],"iteration":144,"passed_time":1.797970709,"remaining_time":10.60182728},
{"learn":[0.4524456597],"iteration":145,"passed_time":1.809311037,"remaining_time":10.58323031},
{"learn":[0.4504170372],"iteration":146,"passed_time":1.820465002,"remaining_time":10.56365066},
{"learn":[0.4468474413],"iteration":147,"passed_time":1.830345559,"remaining_time":10.53685416},
{"learn":[0.4448549203],"iteration":148,"passed_time":1.843001673,"remaining_time":10.52613707},
{"learn":[0.4415340324],"iteration":149,"passed_time":1.854072931,"remaining_time":10.50641328},
{"learn":[0.4400015026],"iteration":150,"passed_time":1.862552633,"remaining_time":10.47223302},
{"learn":[0.437768412],"iteration":151,"passed_time":1.872977502,"remaining_time":10.44924291},
{"learn":[0.4354481609],"iteration":152,"passed_time":1.88379097,"remaining_time":10.42856831},
{"learn":[0.4332566056],"iteration":153,"passed_time":1.894639573,"remaining_time":10.4082148},
{"learn":[0.4309842294],"iteration":154,"passed_time":1.905531739,"remaining_time":10.38822142},
{"learn":[0.4282449688],"iteration":155,"passed_time":1.917330773,"remaining_time":10.3732511},
{"learn":[0.4257830937],"iteration":156,"passed_time":1.928829949,"remaining_time":10.35671113},
{"learn":[0.4243633573],"iteration":157,"passed_time":1.940973773,"remaining_time":10.34367036},
{"learn":[0.4219238476],"iteration":158,"passed_time":1.953004877,"remaining_time":10.33004466},
{"learn":[0.419933645],"iteration":159,"passed_time":1.962585625,"remaining_time":10.30357453},
{"learn":[0.4176805094],"iteration":160,"passed_time":1.972988342,"remaining_time":10.28159764},
{"learn":[0.4154504905],"iteration":161,"passed_time":1.983072068,"remaining_time":10.25811354},
{"learn":[0.4147573689],"iteration":162,"passed_time":1.994953503,"remaining_time":10.24402504},
{"learn":[0.4126860283],"iteration":163,"passed_time":2.005351667,"remaining_time":10.2224024},
{"learn":[0.410580207],"iteration":164,"passed_time":2.01850248,"remaining_time":10.21484588},
{"learn":[0.4079584977],"iteration":165,"passed_time":2.033980351,"remaining_time":10.21891333},
{"learn":[0.405930075],"iteration":166,"passed_time":2.047278039,"remaining_time":10.2118719},
{"learn":[0.4032573754],"iteration":167,"passed_time":2.061016099,"remaining_time":10.20693687},
{"learn":[0.4011463921],"iteration":168,"passed_time":2.074482515,"remaining_time":10.20056195},
{"learn":[0.39930474],"iteration":169,"passed_time":2.085221497,"remaining_time":10.18078731},
{"learn":[0.3972281225],"iteration":170,"passed_time":2.096578624,"remaining_time":10.16411508},
{"learn":[0.3953420031],"iteration":171,"passed_time":2.107024751,"remaining_time":10.14311915},
{"learn":[0.3930507028],"iteration":172,"passed_time":2.118417902,"remaining_time":10.12677228},
{"learn":[0.3916665156],"iteration":173,"passed_time":2.129436573,"remaining_time":10.10870465},
{"learn":[0.390024302],"iteration":174,"passed_time":2.140853893,"remaining_time":10.09259692},
{"learn":[0.3878380024],"iteration":175,"passed_time":2.15081127,"remaining_time":10.06970731},
{"learn":[0.3859207896],"iteration":176,"passed_time":2.160756328,"remaining_time":10.04690654},
{"learn":[0.3840446415],"iteration":177,"passed_time":2.172774784,"remaining_time":10.03382513},
{"learn":[0.3822803677],"iteration":178,"passed_time":2.18350518,"remaining_time":10.01484778},
{"learn":[0.3810098302],"iteration":179,"passed_time":2.195111621,"remaining_time":9.999952942},
{"learn":[0.3790280151],"iteration":180,"passed_time":2.206753026,"remaining_time":9.985252645},
{"learn":[0.3776813226],"iteration":181,"passed_time":2.218187116,"remaining_time":9.96965418},
{"learn":[0.3760228851],"iteration":182,"passed_time":2.230074773,"remaining_time":9.956126174},
{"learn":[0.3748490767],"iteration":183,"passed_time":2.242312773,"remaining_time":9.944169687},
{"learn":[0.3736208187],"iteration":184,"passed_time":2.253878326,"remaining_time":9.929247761},
{"learn":[0.3722293652],"iteration":185,"passed_time":2.265489367,"remaining_time":9.914560995},
{"learn":[0.3703243365],"iteration":186,"passed_time":2.277921474,"remaining_time":9.903476782},
{"learn":[0.3693186466],"iteration":187,"passed_time":2.290025862,"remaining_time":9.890962766},
{"learn":[0.3679239969],"iteration":188,"passed_time":2.302416457,"remaining_time":9.879681201},
{"learn":[0.3660369079],"iteration":189,"passed_time":2.313915753,"remaining_time":9.864588212},
{"learn":[0.364239386],"iteration":190,"passed_time":2.325179661,"remaining_time":9.84853584},
{"learn":[0.3628001327],"iteration":191,"passed_time":2.335903621,"remaining_time":9.830261073},
{"learn":[0.3620682821],"iteration":192,"passed_time":2.347970271,"remaining_time":9.8176788},
{"learn":[0.3598055463],"iteration":193,"passed_time":2.359923602,"remaining_time":9.804631049},
{"learn":[0.358513807],"iteration":194,"passed_time":2.371750482,"remaining_time":9.791072503},
{"learn":[0.3560601782],"iteration":195,"passed_time":2.382626925,"remaining_time":9.773632894},
{"learn":[0.3540658942],"iteration":196,"passed_time":2.39479335,"remaining_time":9.761518073},
{"learn":[0.3532791996],"iteration":197,"passed_time":2.407256023,"remaining_time":9.750602677},
{"learn":[0.3519656135],"iteration":198,"passed_time":2.41874181,"remaining_time":9.735739648},
{"learn":[0.3510560619],"iteration":199,"passed_time":2.430350587,"remaining_time":9.721402347},
{"learn":[0.3498214461],"iteration":200,"passed_time":2.442381636,"remaining_time":9.708770781},
{"learn":[0.3482085167],"iteration":201,"passed_time":2.454992619,"remaining_time":9.698436189},
{"learn":[0.34773968],"iteration":202,"passed_time":2.466790112,"remaining_time":9.684885317},
{"learn":[0.3465409387],"iteration":203,"passed_time":2.477294552,"remaining_time":9.666306194},
{"learn":[0.3451834217],"iteration":204,"passed_time":2.487965006,"remaining_time":9.648449659},
{"learn":[0.3437191858],"iteration":205,"passed_time":2.500223329,"remaining_time":9.636783121},
{"learn":[0.3423085312],"iteration":206,"passed_time":2.511701935,"remaining_time":9.622123837},
{"learn":[0.3408459921],"iteration":207,"passed_time":2.526125983,"remaining_time":9.618710475},
{"learn":[0.3396068568],"iteration":208,"passed_time":2.537557237,"remaining_time":9.603864948},
{"learn":[0.3376984762],"iteration":209,"passed_time":2.548208374,"remaining_time":9.586117217},
{"learn":[0.3362643891],"iteration":210,"passed_time":2.560583892,"remaining_time":9.574884789},
{"learn":[0.3351524204],"iteration":211,"passed_time":2.572505992,"remaining_time":9.561956236},
{"learn":[0.3335846621],"iteration":212,"passed_time":2.583292615,"remaining_time":9.544841726},
{"learn":[0.3328551392],"iteration":213,"passed_time":2.59595386,"remaining_time":9.534671654},
{"learn":[0.3319810756],"iteration":214,"passed_time":2.607433173,"remaining_time":9.52016298},
{"learn":[0.3300738537],"iteration":215,"passed_time":2.61777142,"remaining_time":9.501540709},
{"learn":[0.3290472572],"iteration":216,"passed_time":2.630693741,"remaining_time":9.492318891},
{"learn":[0.3282775405],"iteration":217,"passed_time":2.642360138,"remaining_time":9.478557928},
{"learn":[0.3267091005],"iteration":218,"passed_time":2.653803025,"remaining_time":9.464019008},
{"learn":[0.3252435432],"iteration":219,"passed_time":2.667111842,"remaining_time":9.456123802},
{"learn":[0.3235738038],"iteration":220,"passed_time":2.680795579,"remaining_time":9.449501159},
{"learn":[0.3221050171],"iteration":221,"passed_time":2.692361405,"remaining_time":9.435392672},
{"learn":[0.3214836863],"iteration":222,"passed_time":2.704000201,"remaining_time":9.421561238},
{"learn":[0.3201200343],"iteration":223,"passed_time":2.715629678,"remaining_time":9.407717098},
{"learn":[0.3183876024],"iteration":224,"passed_time":2.729226698,"remaining_time":9.400669737},
{"learn":[0.3170167627],"iteration":225,"passed_time":2.742007853,"remaining_time":9.390770256},
{"learn":[0.3158145914],"iteration":226,"passed_time":2.752820291,"remaining_time":9.374141344},
{"learn":[0.3149502631],"iteration":227,"passed_time":2.763927912,"remaining_time":9.358562929},
{"learn":[0.3138961117],"iteration":228,"passed_time":2.77567182,"remaining_time":9.345165821},
{"learn":[0.3125888848],"iteration":229,"passed_time":2.787479247,"remaining_time":9.331995741},
{"learn":[0.311975602],"iteration":230,"passed_time":2.79966045,"remaining_time":9.320081758},
{"learn":[0.3113854691],"iteration":231,"passed_time":2.811777624,"remaining_time":9.307953514},
{"learn":[0.3104561094],"iteration":232,"passed_time":2.824463595,"remaining_time":9.297697757},
{"learn":[0.3088489084],"iteration":233,"passed_time":2.836173925,"remaining_time":9.284227463},
{"learn":[0.3073303953],"iteration":234,"passed_time":2.849779857,"remaining_time":9.276942938},
{"learn":[0.3063484612],"iteration":235,"passed_time":2.861201901,"remaining_time":9.262534969},
{"learn":[0.3054484211],"iteration":236,"passed_time":2.873489994,"remaining_time":9.250940359},
{"learn":[0.3050998637],"iteration":237,"passed_time":2.885996027,"remaining_time":9.2400377},
{"learn":[0.3030879272],"iteration":238,"passed_time":2.896202259,"remaining_time":9.221798824},
{"learn":[0.301766472],"iteration":239,"passed_time":2.907865513,"remaining_time":9.208240792},
{"learn":[0.3001803081],"iteration":240,"passed_time":2.918594861,"remaining_time":9.191757258},
{"learn":[0.2993204225],"iteration":241,"passed_time":2.930708788,"remaining_time":9.179658103},
{"learn":[0.2970546041],"iteration":242,"passed_time":2.941428255,"remaining_time":9.163214769},
{"learn":[0.2960706911],"iteration":243,"passed_time":2.95250554,"remaining_time":9.147927001},
{"learn":[0.2950775456],"iteration":244,"passed_time":2.964059986,"remaining_time":9.134144037},
{"learn":[0.2939317637],"iteration":245,"passed_time":2.975812668,"remaining_time":9.120986795},
{"learn":[0.2934526179],"iteration":246,"passed_time":2.988413842,"remaining_time":9.110427624},
{"learn":[0.2924341146],"iteration":247,"passed_time":3.001307125,"remaining_time":9.100737733},
{"learn":[0.2910972441],"iteration":248,"passed_time":3.013505438,"remaining_time":9.08892604},
{"learn":[0.2893181326],"iteration":249,"passed_time":3.024317074,"remaining_time":9.072951221},
{"learn":[0.2882061337],"iteration":250,"passed_time":3.034855386,"remaining_time":9.056201928},
{"learn":[0.286955092],"iteration":251,"passed_time":3.048869694,"remaining_time":9.049819568},
{"learn":[0.2860656413],"iteration":252,"passed_time":3.058472895,"remaining_time":9.030352778},
{"learn":[0.2855161457],"iteration":253,"passed_time":3.072960157,"remaining_time":9.025308177},
{"learn":[0.2842239562],"iteration":254,"passed_time":3.086502647,"remaining_time":9.017429301},
{"learn":[0.2834825637],"iteration":255,"passed_time":3.10089992,"remaining_time":9.011990392},
{"learn":[0.2820555377],"iteration":256,"passed_time":3.11545927,"remaining_time":9.00695034},
{"learn":[0.2803716265],"iteration":257,"passed_time":3.129980518,"remaining_time":9.001726917},
{"learn":[0.2795825177],"iteration":258,"passed_time":3.143193116,"remaining_time":8.992687641},
{"learn":[0.2781668335],"iteration":259,"passed_time":3.169540428,"remaining_time":9.020999681},
{"learn":[0.2774448616],"iteration":260,"passed_time":3.181716708,"remaining_time":9.008768762},
{"learn":[0.276174705],"iteration":261,"passed_time":3.193108275,"remaining_time":8.99432789},
{"learn":[0.2751835052],"iteration":262,"passed_time":3.204418672,"remaining_time":8.979682742},
{"learn":[0.2745054934],"iteration":263,"passed_time":3.215701658,"remaining_time":8.964986439},
{"learn":[0.2735691717],"iteration":264,"passed_time":3.227141575,"remaining_time":8.950751162},
{"learn":[0.2725569389],"iteration":265,"passed_time":3.238855028,"remaining_time":8.937291694},
{"learn":[0.2715855678],"iteration":266,"passed_time":3.250507455,"remaining_time":8.923677768},
{"learn":[0.270644698],"iteration":267,"passed_time":3.261803117,"remaining_time":8.909104035},
{"learn":[0.2695936173],"iteration":268,"passed_time":3.273899954,"remaining_time":8.896731846},
{"learn":[0.2682534952],"iteration":269,"passed_time":3.285930718,"remaining_time":8.884183052},
{"learn":[0.2677272788],"iteration":270,"passed_time":3.297182708,"remaining_time":8.869543151},
{"learn":[0.2667450388],"iteration":271,"passed_time":3.30933145,"remaining_time":8.857328293},
{"learn":[0.2650755923],"iteration":272,"passed_time":3.320689329,"remaining_time":8.843007846},
{"learn":[0.2639275442],"iteration":273,"passed_time":3.332090894,"remaining_time":8.828824778},
{"learn":[0.2631126805],"iteration":274,"passed_time":3.343719354,"remaining_time":8.815260116},
{"learn":[0.2621402004],"iteration":275,"passed_time":3.355736423,"remaining_time":8.802728878},
{"learn":[0.2613340146],"iteration":276,"passed_time":3.367148268,"remaining_time":8.788621652},
{"learn":[0.2602937637],"iteration":277,"passed_time":3.379003352,"remaining_time":8.775684966},
{"learn":[0.2590892757],"iteration":278,"passed_time":3.39024553,"remaining_time":8.761172139},
{"learn":[0.2578389093],"iteration":279,"passed_time":3.401742668,"remaining_time":8.747338289},
{"learn":[0.257438607],"iteration":280,"passed_time":3.413845169,"remaining_time":8.735070024},
{"learn":[0.2564720704],"iteration":281,"passed_time":3.425739465,"remaining_time":8.722272823},
{"learn":[0.2558451802],"iteration":282,"passed_time":3.438251905,"remaining_time":8.711048114},
{"learn":[0.2545389795],"iteration":283,"passed_time":3.450143492,"remaining_time":8.698249085},
{"learn":[0.253965304],"iteration":284,"passed_time":3.46112315,"remaining_time":8.683168605},
{"learn":[0.2530763264],"iteration":285,"passed_time":3.473150422,"remaining_time":8.670732173},
{"learn":[0.252223643],"iteration":286,"passed_time":3.486095358,"remaining_time":8.660578364},
{"learn":[0.2513523096],"iteration":287,"passed_time":3.497941032,"remaining_time":8.64768755},
{"learn":[0.2502637848],"iteration":288,"passed_time":3.508854362,"remaining_time":8.632510212},
{"learn":[0.2492414605],"iteration":289,"passed_time":3.520748027,"remaining_time":8.61976241},
{"learn":[0.2482794992],"iteration":290,"passed_time":3.532546737,"remaining_time":8.606789129},
{"learn":[0.2473384486],"iteration":291,"passed_time":3.543851703,"remaining_time":8.592626731},
{"learn":[0.2463160932],"iteration":292,"passed_time":3.554939556,"remaining_time":8.577959954},
{"learn":[0.2453944074],"iteration":293,"passed_time":3.566840541,"remaining_time":8.565270143},
{"learn":[0.2444291655],"iteration":294,"passed_time":3.579440714,"remaining_time":8.554256623},
{"learn":[0.2431641959],"iteration":295,"passed_time":3.591236876,"remaining_time":8.541320138},
{"learn":[0.2423667772],"iteration":296,"passed_time":3.602400936,"remaining_time":8.526895146},
{"learn":[0.2413634984],"iteration":297,"passed_time":3.61367324,"remaining_time":8.512747028},
{"learn":[0.2407124535],"iteration":298,"passed_time":3.624810987,"remaining_time":8.498302681},
{"learn":[0.2399922695],"iteration":299,"passed_time":3.636082577,"remaining_time":8.484192679},
{"learn":[0.239387791],"iteration":300,"passed_time":3.647910277,"remaining_time":8.471392969},
{"learn":[0.2385686087],"iteration":301,"passed_time":3.659653143,"remaining_time":8.458403622},
{"learn":[0.2381964992],"iteration":302,"passed_time":3.67133085,"remaining_time":8.445272616},
{"learn":[0.2376181197],"iteration":303,"passed_time":3.694269929,"remaining_time":8.457933785},
{"learn":[0.2366975706],"iteration":304,"passed_time":3.706612513,"remaining_time":8.4462154},
{"learn":[0.2357805866],"iteration":305,"passed_time":3.71882929,"remaining_time":8.434207605},
{"learn":[0.2346783267],"iteration":306,"passed_time":3.731532607,"remaining_time":8.423296731},
{"learn":[0.2339049739],"iteration":307,"passed_time":3.743285857,"remaining_time":8.410239653},
{"learn":[0.2331962482],"iteration":308,"passed_time":3.752743556,"remaining_time":8.392057596},
{"learn":[0.2324849885],"iteration":309,"passed_time":3.763120758,"remaining_time":8.375978461},
{"learn":[0.2316054688],"iteration":310,"passed_time":3.775940552,"remaining_time":8.365347396},
{"learn":[0.230646952],"iteration":311,"passed_time":3.787655351,"remaining_time":8.352265645},
{"learn":[0.2297120603],"iteration":312,"passed_time":3.802189236,"remaining_time":8.345380208},
{"learn":[0.2293061947],"iteration":313,"passed_time":3.816867001,"remaining_time":8.338760391},
{"learn":[0.2277561838],"iteration":314,"passed_time":3.831894179,"remaining_time":8.332849247},
{"learn":[0.226371624],"iteration":315,"passed_time":3.84545052,"remaining_time":8.323696694},
{"learn":[0.2258213646],"iteration":316,"passed_time":3.85812149,"remaining_time":8.312608762},
{"learn":[0.2248512232],"iteration":317,"passed_time":3.86915157,"remaining_time":8.297991732},
{"learn":[0.2236893456],"iteration":318,"passed_time":3.880094064,"remaining_time":8.283210212},
{"learn":[0.222886251],"iteration":319,"passed_time":3.891340569,"remaining_time":8.269098709},
{"learn":[0.2220534433],"iteration":320,"passed_time":3.903126505,"remaining_time":8.256146096},
{"learn":[0.2212126156],"iteration":321,"passed_time":3.914626547,"remaining_time":8.242598754},
{"learn":[0.2203529608],"iteration":322,"passed_time":3.92646941,"remaining_time":8.229782634},
{"learn":[0.2197269957],"iteration":323,"passed_time":3.938104571,"remaining_time":8.216539166},
{"learn":[0.2189533406],"iteration":324,"passed_time":3.950574825,"remaining_time":8.20504002},
{"learn":[0.217873424],"iteration":325,"passed_time":3.961578372,"remaining_time":8.190502523},
{"learn":[0.2173127406],"iteration":326,"passed_time":3.973119731,"remaining_time":8.177093513},
{"learn":[0.2165550904],"iteration":327,"passed_time":3.984907762,"remaining_time":8.164201268},
{"learn":[0.2159791258],"iteration":328,"passed_time":3.996050044,"remaining_time":8.149998722},
{"learn":[0.2152082366],"iteration":329,"passed_time":4.007178281,"remaining_time":8.135786207},
{"learn":[0.2149529985],"iteration":330,"passed_time":4.019203603,"remaining_time":8.123405469},
{"learn":[0.2144269905],"iteration":331,"passed_time":4.030795238,"remaining_time":8.110154275},
{"learn":[0.2133201064],"iteration":332,"passed_time":4.042237982,"remaining_time":8.096614816},
{"learn":[0.2127143135],"iteration":333,"passed_time":4.052978836,"remaining_time":8.081688337},
{"learn":[0.2122579301],"iteration":334,"passed_time":4.06544669,"remaining_time":8.070215071},
{"learn":[0.2116078432],"iteration":335,"passed_time":4.078619754,"remaining_time":8.060129513},
{"learn":[0.2106120667],"iteration":336,"passed_time":4.093215532,"remaining_time":8.052824622},
{"learn":[0.2102512451],"iteration":337,"passed_time":4.10530458,"remaining_time":8.040566959},
{"learn":[0.2096830741],"iteration":338,"passed_time":4.117969623,"remaining_time":8.029433396},
{"learn":[0.208741697],"iteration":339,"passed_time":4.128876876,"remaining_time":8.014878641},
{"learn":[0.207972204],"iteration":340,"passed_time":4.140385115,"remaining_time":8.001506718},
{"learn":[0.2074242251],"iteration":341,"passed_time":4.151478883,"remaining_time":7.98734826},
{"learn":[0.2067208827],"iteration":342,"passed_time":4.163740713,"remaining_time":7.975445039},
{"learn":[0.205948497],"iteration":343,"passed_time":4.175304333,"remaining_time":7.962208262},
{"learn":[0.2053174711],"iteration":344,"passed_time":4.186759236,"remaining_time":7.948774781},
{"learn":[0.2048145944],"iteration":345,"passed_time":4.198974723,"remaining_time":7.936790372},
{"learn":[0.2039152607],"iteration":346,"passed_time":4.209527387,"remaining_time":7.921675458},
{"learn":[0.2031003422],"iteration":347,"passed_time":4.220826118,"remaining_time":7.907984565},
{"learn":[0.2022029048],"iteration":348,"passed_time":4.232067187,"remaining_time":7.894199825},
{"learn":[0.2017073418],"iteration":349,"passed_time":4.243867012,"remaining_time":7.881467308},
{"learn":[0.2009743312],"iteration":350,"passed_time":4.255888859,"remaining_time":7.869150625},
{"learn":[0.2005999162],"iteration":351,"passed_time":4.267264016,"remaining_time":7.855645121},
{"learn":[0.1998986236],"iteration":352,"passed_time":4.279102913,"remaining_time":7.843001656},
{"learn":[0.1992980884],"iteration":353,"passed_time":4.290148091,"remaining_time":7.828914313},
{"learn":[0.198826279],"iteration":354,"passed_time":4.301497396,"remaining_time":7.815396678},
{"learn":[0.1981683455],"iteration":355,"passed_time":4.313531856,"remaining_time":7.803130661},
{"learn":[0.1980350084],"iteration":356,"passed_time":4.317482424,"remaining_time":7.776305878},
{"learn":[0.1974202198],"iteration":357,"passed_time":4.329216626,"remaining_time":7.763567245},
{"learn":[0.1967009646],"iteration":358,"passed_time":4.340016251,"remaining_time":7.749165506},
{"learn":[0.1959913856],"iteration":359,"passed_time":4.352218959,"remaining_time":7.73727815},
{"learn":[0.1947743805],"iteration":360,"passed_time":4.363440448,"remaining_time":7.723652206},
{"learn":[0.1942144641],"iteration":361,"passed_time":4.374392118,"remaining_time":7.709564009},
{"learn":[0.1937108707],"iteration":362,"passed_time":4.384791757,"remaining_time":7.694524379},
{"learn":[0.1929255644],"iteration":363,"passed_time":4.396210586,"remaining_time":7.681291024},
{"learn":[0.1923400533],"iteration":364,"passed_time":4.40757308,"remaining_time":7.667969604},
{"learn":[0.1916235062],"iteration":365,"passed_time":4.419058881,"remaining_time":7.654872487},
{"learn":[0.1910995951],"iteration":366,"passed_time":4.430471878,"remaining_time":7.64165858},
{"learn":[0.1909030328],"iteration":367,"passed_time":4.441579118,"remaining_time":7.627929355},
{"learn":[0.1900814254],"iteration":368,"passed_time":4.453374218,"remaining_time":7.615390601},
{"learn":[0.1894653092],"iteration":369,"passed_time":4.466468243,"remaining_time":7.605067549},
{"learn":[0.188755036],"iteration":370,"passed_time":4.479680934,"remaining_time":7.594930748},
{"learn":[0.1882201856],"iteration":371,"passed_time":4.492845768,"remaining_time":7.584696619},
{"learn":[0.18759152],"iteration":372,"passed_time":4.506385263,"remaining_time":7.575076567},
{"learn":[0.1870391469],"iteration":373,"passed_time":4.518964695,"remaining_time":7.563828607},
{"learn":[0.1866780892],"iteration":374,"passed_time":4.532266578,"remaining_time":7.55377763},
{"learn":[0.1862545944],"iteration":375,"passed_time":4.544802242,"remaining_time":7.542437763},
{"learn":[0.1854535287],"iteration":376,"passed_time":4.557128137,"remaining_time":7.530744906},
{"learn":[0.1849970491],"iteration":377,"passed_time":4.568816675,"remaining_time":7.517999926},
{"learn":[0.1846973891],"iteration":378,"passed_time":4.579990923,"remaining_time":7.504417845},
{"learn":[0.1841103794],"iteration":379,"passed_time":4.594712734,"remaining_time":7.496636565},
{"learn":[0.1837836496],"iteration":380,"passed_time":4.609513664,"remaining_time":7.488947396},
{"learn":[0.183587511],"iteration":381,"passed_time":4.624677892,"remaining_time":7.481808737},
{"learn":[0.18322809],"iteration":382,"passed_time":4.638570241,"remaining_time":7.472579213},
{"learn":[0.1827672719],"iteration":383,"passed_time":4.652199309,"remaining_time":7.462903058},
{"learn":[0.1821241677],"iteration":384,"passed_time":4.663838238,"remaining_time":7.450027315},
{"learn":[0.1815888424],"iteration":385,"passed_time":4.67538237,"remaining_time":7.437007189},
{"learn":[0.1808400826],"iteration":386,"passed_time":4.687675352,"remaining_time":7.425180854},
{"learn":[0.1799622463],"iteration":387,"passed_time":4.698621203,"remaining_time":7.411227259},
{"learn":[0.1791077191],"iteration":388,"passed_time":4.710634241,"remaining_time":7.39896535},
{"learn":[0.1785771132],"iteration":389,"passed_time":4.721895546,"remaining_time":7.385528932},
{"learn":[0.1779644454],"iteration":390,"passed_time":4.733448211,"remaining_time":7.372557443},
{"learn":[0.1770549027],"iteration":391,"passed_time":4.744667023,"remaining_time":7.359075382},
{"learn":[0.1767954302],"iteration":392,"passed_time":4.756551436,"remaining_time":7.346632879},
{"learn":[0.1759864205],"iteration":393,"passed_time":4.768614754,"remaining_time":7.334468378},
{"learn":[0.1755456625],"iteration":394,"passed_time":4.780997282,"remaining_time":7.322793305},
{"learn":[0.1747718264],"iteration":395,"passed_time":4.792163223,"remaining_time":7.309259058},
{"learn":[0.174149815],"iteration":396,"passed_time":4.80441205,"remaining_time":7.297381527},
{"learn":[0.1737690056],"iteration":397,"passed_time":4.815957242,"remaining_time":7.284437839},
{"learn":[0.1735318377],"iteration":398,"passed_time":4.827663928,"remaining_time":7.271744413},
{"learn":[0.173230815],"iteration":399,"passed_time":4.839370392,"remaining_time":7.259055588},
{"learn":[0.1725483864],"iteration":400,"passed_time":4.851382203,"remaining_time":7.246827779},
{"learn":[0.1721858872],"iteration":401,"passed_time":4.862203817,"remaining_time":7.232830553},
{"learn":[0.1717483403],"iteration":402,"passed_time":4.873139022,"remaining_time":7.219017361},
{"learn":[0.171004225],"iteration":403,"passed_time":4.885470253,"remaining_time":7.207277897},
{"learn":[0.1707097362],"iteration":404,"passed_time":4.89727723,"remaining_time":7.194765312},
{"learn":[0.1704039502],"iteration":405,"passed_time":4.90897111,"remaining_time":7.182090737},
{"learn":[0.1702063993],"iteration":406,"passed_time":4.920324888,"remaining_time":7.168925451},
{"learn":[0.1698083229],"iteration":407,"passed_time":4.932437978,"remaining_time":7.156870791},
{"learn":[0.1691987614],"iteration":408,"passed_time":4.944214006,"remaining_time":7.144328796},
{"learn":[0.1684401635],"iteration":409,"passed_time":4.955439069,"remaining_time":7.130997684},
{"learn":[0.1680029466],"iteration":410,"passed_time":4.967140471,"remaining_time":7.118359459},
{"learn":[0.1674028697],"iteration":411,"passed_time":4.978524816,"remaining_time":7.105273281},
{"learn":[0.1667685936],"iteration":412,"passed_time":4.990326453,"remaining_time":7.092788445},
{"learn":[0.1661639899],"iteration":413,"passed_time":5.002534235,"remaining_time":7.080881791},
{"learn":[0.1655898488],"iteration":414,"passed_time":5.016690153,"remaining_time":7.071719854},
{"learn":[0.1650635855],"iteration":415,"passed_time":5.028000863,"remaining_time":7.058539673},
{"learn":[0.1646219308],"iteration":416,"passed_time":5.040482102,"remaining_time":7.047004953},
{"learn":[0.1641897304],"iteration":417,"passed_time":5.0514912,"remaining_time":7.033415978},
{"learn":[0.163667882],"iteration":418,"passed_time":5.062367792,"remaining_time":7.019655578},
{"learn":[0.1629209242],"iteration":419,"passed_time":5.074102787,"remaining_time":7.007094324},
{"learn":[0.1624940525],"iteration":420,"passed_time":5.08627646,"remaining_time":6.995140309},
{"learn":[0.1621262405],"iteration":421,"passed_time":5.098209071,"remaining_time":6.982855078},
{"learn":[0.1618479172],"iteration":422,"passed_time":5.109832101,"remaining_time":6.970149225},
{"learn":[0.1615182402],"iteration":423,"passed_time":5.122352372,"remaining_time":6.958667373},
{"learn":[0.1609644795],"iteration":424,"passed_time":5.133809798,"remaining_time":6.945742668},
{"learn":[0.1605485026],"iteration":425,"passed_time":5.145584194,"remaining_time":6.933251942},
{"learn":[0.1603452614],"iteration":426,"passed_time":5.156585831,"remaining_time":6.91972759},
{"learn":[0.1597307344],"iteration":427,"passed_time":5.168125815,"remaining_time":6.906934501},
{"learn":[0.1592192646],"iteration":428,"passed_time":5.178433214,"remaining_time":6.892506679},
{"learn":[0.1589178792],"iteration":429,"passed_time":5.190157655,"remaining_time":6.879976426},
{"learn":[0.1581685631],"iteration":430,"passed_time":5.201291762,"remaining_time":6.866670563},
{"learn":[0.1575996186],"iteration":431,"passed_time":5.212904029,"remaining_time":6.854003445},
{"learn":[0.157141079],"iteration":432,"passed_time":5.224995003,"remaining_time":6.841968052},
{"learn":[0.1567846595],"iteration":433,"passed_time":5.236647723,"remaining_time":6.829360855},
{"learn":[0.1561991998],"iteration":434,"passed_time":5.247776379,"remaining_time":6.816077365},
{"learn":[0.1554709167],"iteration":435,"passed_time":5.260257049,"remaining_time":6.804552696},
{"learn":[0.1551211854],"iteration":436,"passed_time":5.271760999,"remaining_time":6.791765314},
{"learn":[0.1546731592],"iteration":437,"passed_time":5.284995561,"remaining_time":6.78120435},
{"learn":[0.1541080053],"iteration":438,"passed_time":5.2979604,"remaining_time":6.770286524},
{"learn":[0.1535410151],"iteration":439,"passed_time":5.309679641,"remaining_time":6.757774089},
{"learn":[0.1529753284],"iteration":440,"passed_time":5.320690575,"remaining_time":6.744367419},
{"learn":[0.152708793],"iteration":441,"passed_time":5.333226628,"remaining_time":6.732896965},
{"learn":[0.1524102988],"iteration":442,"passed_time":5.345316911,"remaining_time":6.720861218},
{"learn":[0.1518828003],"iteration":443,"passed_time":5.357548795,"remaining_time":6.709002545},
{"learn":[0.1514710189],"iteration":444,"passed_time":5.369757096,"remaining_time":6.697112783},
{"learn":[0.1508946244],"iteration":445,"passed_time":5.380810297,"remaining_time":6.683786782},
{"learn":[0.1503658778],"iteration":446,"passed_time":5.391846341,"remaining_time":6.670449724},
{"learn":[0.1500098197],"iteration":447,"passed_time":5.402597798,"remaining_time":6.656772287},
{"learn":[0.1495375262],"iteration":448,"passed_time":5.414506495,"remaining_time":6.644528015},
{"learn":[0.1493640908],"iteration":449,"passed_time":5.426171502,"remaining_time":6.631987391},
{"learn":[0.1490423627],"iteration":450,"passed_time":5.437421475,"remaining_time":6.618945432},
{"learn":[0.1486252547],"iteration":451,"passed_time":5.448783746,"remaining_time":6.606047551},
{"learn":[0.1482781172],"iteration":452,"passed_time":5.46054328,"remaining_time":6.593636146},
{"learn":[0.1479759166],"iteration":453,"passed_time":5.472074743,"remaining_time":6.580953325},
{"learn":[0.1475740456],"iteration":454,"passed_time":5.48297777,"remaining_time":6.567522824},
{"learn":[0.1472044059],"iteration":455,"passed_time":5.494592386,"remaining_time":6.55495232},
{"learn":[0.1468730936],"iteration":456,"passed_time":5.506219565,"remaining_time":6.542400928},
{"learn":[0.1466686609],"iteration":457,"passed_time":5.517687428,"remaining_time":6.529665035},
{"learn":[0.1463452847],"iteration":458,"passed_time":5.528941816,"remaining_time":6.516683056},
{"learn":[0.1459075425],"iteration":459,"passed_time":5.541084742,"remaining_time":6.504751653},
{"learn":[0.1455037337],"iteration":460,"passed_time":5.55203968,"remaining_time":6.491430342},
{"learn":[0.1452995504],"iteration":461,"passed_time":5.563601661,"remaining_time":6.478826177},
{"learn":[0.1448006485],"iteration":462,"passed_time":5.575502905,"remaining_time":6.466619999},
{"learn":[0.1443599413],"iteration":463,"passed_time":5.586845244,"remaining_time":6.453769507},
{"learn":[0.1440111827],"iteration":464,"passed_time":5.598694274,"remaining_time":6.441508466},
{"learn":[0.1435893579],"iteration":465,"passed_time":5.610602832,"remaining_time":6.429317408},
{"learn":[0.1432012286],"iteration":466,"passed_time":5.62143813,"remaining_time":6.415902619},
{"learn":[0.1429850161],"iteration":467,"passed_time":5.633463485,"remaining_time":6.403851654},
{"learn":[0.1426306626],"iteration":468,"passed_time":5.644881358,"remaining_time":6.391113008},
{"learn":[0.1423555317],"iteration":469,"passed_time":5.656832116,"remaining_time":6.378980897},
{"learn":[0.1421460207],"iteration":470,"passed_time":5.667898905,"remaining_time":6.365856732},
{"learn":[0.1415520167],"iteration":471,"passed_time":5.679770309,"remaining_time":6.353641363},
{"learn":[0.1406703426],"iteration":472,"passed_time":5.691701086,"remaining_time":6.341493599},
{"learn":[0.1400987175],"iteration":473,"passed_time":5.704063987,"remaining_time":6.329826281},
{"learn":[0.1397457042],"iteration":474,"passed_time":5.715659245,"remaining_time":6.317307587},
{"learn":[0.1394174421],"iteration":475,"passed_time":5.727430248,"remaining_time":6.30498624},
{"learn":[0.1389595026],"iteration":476,"passed_time":5.739405974,"remaining_time":6.292891666},
{"learn":[0.1383870323],"iteration":477,"passed_time":5.750473755,"remaining_time":6.279806067},
{"learn":[0.1379823747],"iteration":478,"passed_time":5.7616046,"remaining_time":6.266797488},
{"learn":[0.1377897809],"iteration":479,"passed_time":5.773056703,"remaining_time":6.254144762},
{"learn":[0.1373158452],"iteration":480,"passed_time":5.785421591,"remaining_time":6.242481925},
{"learn":[0.136977953],"iteration":481,"passed_time":5.796244192,"remaining_time":6.229158695},
{"learn":[0.1366171897],"iteration":482,"passed_time":5.808415914,"remaining_time":6.217289912},
{"learn":[0.1362650093],"iteration":483,"passed_time":5.820118723,"remaining_time":6.20491996},
{"learn":[0.1359349395],"iteration":484,"passed_time":5.831872058,"remaining_time":6.192606412},
{"learn":[0.1355703462],"iteration":485,"passed_time":5.844059636,"remaining_time":6.18075443},
{"learn":[0.1352947327],"iteration":486,"passed_time":5.85531727,"remaining_time":6.167921478},
{"learn":[0.1351455863],"iteration":487,"passed_time":5.865678879,"remaining_time":6.154154889},
{"learn":[0.1347975667],"iteration":488,"passed_time":5.87762839,"remaining_time":6.142061569},
{"learn":[0.1345999271],"iteration":489,"passed_time":5.890227589,"remaining_time":6.130645042},
{"learn":[0.1343317094],"iteration":490,"passed_time":5.901912774,"remaining_time":6.118276175},
{"learn":[0.1340809128],"iteration":491,"passed_time":5.913221827,"remaining_time":6.105521723},
{"learn":[0.1337367562],"iteration":492,"passed_time":5.92461119,"remaining_time":6.092855727},
{"learn":[0.1333035919],"iteration":493,"passed_time":5.935841538,"remaining_time":6.080032021},
{"learn":[0.1328638631],"iteration":494,"passed_time":5.947746328,"remaining_time":6.06790282},
{"learn":[0.1324389354],"iteration":495,"passed_time":5.959775709,"remaining_time":6.055901124},
{"learn":[0.1320720705],"iteration":496,"passed_time":5.970974806,"remaining_time":6.043059009},
{"learn":[0.1318340891],"iteration":497,"passed_time":5.983550605,"remaining_time":6.031611252},
{"learn":[0.1314182893],"iteration":498,"passed_time":5.994542878,"remaining_time":6.018569102},
{"learn":[0.131150967],"iteration":499,"passed_time":6.006458205,"remaining_time":6.006458205},
{"learn":[0.130804943],"iteration":500,"passed_time":6.017006559,"remaining_time":5.992986573},
{"learn":[0.130547955],"iteration":501,"passed_time":6.028084308,"remaining_time":5.980051763},
{"learn":[0.1303489513],"iteration":502,"passed_time":6.039148606,"remaining_time":5.967111049},
{"learn":[0.1300853227],"iteration":503,"passed_time":6.051321104,"remaining_time":5.955268388},
{"learn":[0.1299161072],"iteration":504,"passed_time":6.062052919,"remaining_time":5.942012267},
{"learn":[0.1296669881],"iteration":505,"passed_time":6.074215984,"remaining_time":5.930163431},
{"learn":[0.1295184899],"iteration":506,"passed_time":6.086025185,"remaining_time":5.917969263},
{"learn":[0.12924389],"iteration":507,"passed_time":6.102604477,"remaining_time":5.910396462},
{"learn":[0.1288938391],"iteration":508,"passed_time":6.115789959,"remaining_time":5.899514479},
{"learn":[0.128580716],"iteration":509,"passed_time":6.127421751,"remaining_time":5.887130702},
{"learn":[0.1282096895],"iteration":510,"passed_time":6.138987597,"remaining_time":5.874686761},
{"learn":[0.1279529851],"iteration":511,"passed_time":6.157046258,"remaining_time":5.868434714},
{"learn":[0.1275521569],"iteration":512,"passed_time":6.168958368,"remaining_time":5.856301609},
{"learn":[0.1271918421],"iteration":513,"passed_time":6.179510055,"remaining_time":5.842883048},
{"learn":[0.1269334518],"iteration":514,"passed_time":6.190999522,"remaining_time":5.830358773},
{"learn":[0.126672638],"iteration":515,"passed_time":6.202723986,"remaining_time":5.818058933},
{"learn":[0.1264319151],"iteration":516,"passed_time":6.214420061,"remaining_time":5.805734795},
{"learn":[0.1261477135],"iteration":517,"passed_time":6.226592416,"remaining_time":5.793856263},
{"learn":[0.1258624313],"iteration":518,"passed_time":6.238144112,"remaining_time":5.781401383},
{"learn":[0.1257257791],"iteration":519,"passed_time":6.24932829,"remaining_time":5.768610729},
{"learn":[0.1252382538],"iteration":520,"passed_time":6.261009619,"remaining_time":5.756283316},
{"learn":[0.1250170755],"iteration":521,"passed_time":6.273474565,"remaining_time":5.744675942},
{"learn":[0.1246544443],"iteration":522,"passed_time":6.285294751,"remaining_time":5.732477239},
{"learn":[0.1242818854],"iteration":523,"passed_time":6.298247076,"remaining_time":5.721308413},
{"learn":[0.1239532131],"iteration":524,"passed_time":6.310292278,"remaining_time":5.709312061},
{"learn":[0.1235525032],"iteration":525,"passed_time":6.3222979,"remaining_time":5.697279857},
{"learn":[0.1229309745],"iteration":526,"passed_time":6.333922152,"remaining_time":5.684905461},
{"learn":[0.1226672639],"iteration":527,"passed_time":6.346362487,"remaining_time":5.673263435},
{"learn":[0.1224267799],"iteration":528,"passed_time":6.358922607,"remaining_time":5.661725043},
{"learn":[0.1221931684],"iteration":529,"passed_time":6.369820055,"remaining_time":5.64870835},
{"learn":[0.1218190034],"iteration":530,"passed_time":6.380612351,"remaining_time":5.635606766},
{"learn":[0.1216346115],"iteration":531,"passed_time":6.391085795,"remaining_time":5.622233369},
{"learn":[0.1213842012],"iteration":532,"passed_time":6.400546586,"remaining_time":5.607983594},
{"learn":[0.121095242],"iteration":533,"passed_time":6.410010102,"remaining_time":5.593754134},
{"learn":[0.1207963955],"iteration":534,"passed_time":6.420696117,"remaining_time":5.580605036},
{"learn":[0.1205451445],"iteration":535,"passed_time":6.431978081,"remaining_time":5.567981026},
{"learn":[0.1202906436],"iteration":536,"passed_time":6.442800548,"remaining_time":5.554965835},
{"learn":[0.1198619533],"iteration":537,"passed_time":6.453210715,"remaining_time":5.54160474},
{"learn":[0.1196269669],"iteration":538,"passed_time":6.463782035,"remaining_time":5.528392427},
{"learn":[0.1192903427],"iteration":539,"passed_time":6.473547828,"remaining_time":5.514503705},
{"learn":[0.1190842757],"iteration":540,"passed_time":6.483988069,"remaining_time":5.501202446},
{"learn":[0.1188747878],"iteration":541,"passed_time":6.493781574,"remaining_time":5.487365242},
{"learn":[0.1186722569],"iteration":542,"passed_time":6.505605668,"remaining_time":5.475251916},
{"learn":[0.118328126],"iteration":543,"passed_time":6.515496927,"remaining_time":5.461519483},
{"learn":[0.117999263],"iteration":544,"passed_time":6.525240094,"remaining_time":5.44767751},
{"learn":[0.1175260359],"iteration":545,"passed_time":6.534812404,"remaining_time":5.433708483},
{"learn":[0.1172748385],"iteration":546,"passed_time":6.545406797,"remaining_time":5.420601973},
{"learn":[0.1169789714],"iteration":547,"passed_time":6.555841412,"remaining_time":5.407372843},
{"learn":[0.1167628646],"iteration":548,"passed_time":6.565073617,"remaining_time":5.393166122},
{"learn":[0.11632104],"iteration":549,"passed_time":6.574803755,"remaining_time":5.379384891},
{"learn":[0.1158713619],"iteration":550,"passed_time":6.584718874,"remaining_time":5.365769101},
{"learn":[0.1156184619],"iteration":551,"passed_time":6.593668156,"remaining_time":5.351382851},
{"learn":[0.1154094178],"iteration":552,"passed_time":6.60356554,"remaining_time":5.337782634},
{"learn":[0.1150843565],"iteration":553,"passed_time":6.613307541,"remaining_time":5.324070692},
{"learn":[0.1149602015],"iteration":554,"passed_time":6.623311283,"remaining_time":5.310582921},
{"learn":[0.1145833767],"iteration":555,"passed_time":6.634389098,"remaining_time":5.297965395},
{"learn":[0.1143868465],"iteration":556,"passed_time":6.645110029,"remaining_time":5.285069556},
{"learn":[0.114196014],"iteration":557,"passed_time":6.654849531,"remaining_time":5.271404109},
{"learn":[0.1138432021],"iteration":558,"passed_time":6.665554233,"remaining_time":5.258514162},
{"learn":[0.1135631717],"iteration":559,"passed_time":6.675323542,"remaining_time":5.244897068},
{"learn":[0.1133005179],"iteration":560,"passed_time":6.6854436,"remaining_time":5.231568165},
{"learn":[0.1130770695],"iteration":561,"passed_time":6.69572985,"remaining_time":5.218380204},
{"learn":[0.1129398992],"iteration":562,"passed_time":6.705350881,"remaining_time":5.204686207},
{"learn":[0.1127012683],"iteration":563,"passed_time":6.715306909,"remaining_time":5.191265625},
{"learn":[0.112478112],"iteration":564,"passed_time":6.726398039,"remaining_time":5.178731233},
{"learn":[0.1121491332],"iteration":565,"passed_time":6.736912318,"remaining_time":5.165759622},
{"learn":[0.1119554892],"iteration":566,"passed_time":6.746941933,"remaining_time":5.152426555},
{"learn":[0.1116787293],"iteration":567,"passed_time":6.757566401,"remaining_time":5.139557545},
{"learn":[0.1114186705],"iteration":568,"passed_time":6.766546051,"remaining_time":5.125450524},
{"learn":[0.1111983935],"iteration":569,"passed_time":6.777315322,"remaining_time":5.112711559},
{"learn":[0.1110131805],"iteration":570,"passed_time":6.78700601,"remaining_time":5.099169139},
{"learn":[0.110735485],"iteration":571,"passed_time":6.79857399,"remaining_time":5.087044873},
{"learn":[0.1104250457],"iteration":572,"passed_time":6.808559598,"remaining_time":5.073743365},
{"learn":[0.1101223109],"iteration":573,"passed_time":6.820556962,"remaining_time":5.061946456},
{"learn":[0.1098607501],"iteration":574,"passed_time":6.832136875,"remaining_time":5.049840299},
{"learn":[0.1096128297],"iteration":575,"passed_time":6.843701432,"remaining_time":5.037724665},
{"learn":[0.1092267543],"iteration":576,"passed_time":6.85463983,"remaining_time":5.025151903},
{"learn":[0.1090375553],"iteration":577,"passed_time":6.86649099,"remaining_time":5.013251207},
{"learn":[0.108756738],"iteration":578,"passed_time":6.879307956,"remaining_time":5.002052935},
{"learn":[0.1085044346],"iteration":579,"passed_time":6.891974813,"remaining_time":4.990740382},
{"learn":[0.1083762317],"iteration":580,"passed_time":6.904305105,"remaining_time":4.979180446},
{"learn":[0.108094057],"iteration":581,"passed_time":6.91614335,"remaining_time":4.967264468},
{"learn":[0.1078329487],"iteration":582,"passed_time":6.928425243,"remaining_time":4.955666083},
{"learn":[0.1076302004],"iteration":583,"passed_time":6.939793113,"remaining_time":4.943414272},
{"learn":[0.1075204186],"iteration":584,"passed_time":6.951659197,"remaining_time":4.931518917},
{"learn":[0.1074365339],"iteration":585,"passed_time":6.962399966,"remaining_time":4.918828645},
{"learn":[0.1071889042],"iteration":586,"passed_time":6.972862109,"remaining_time":4.90594898},
{"learn":[0.1068486872],"iteration":587,"passed_time":6.9840939,"remaining_time":4.893616814},
{"learn":[0.1065691653],"iteration":588,"passed_time":6.995037005,"remaining_time":4.881086942},
{"learn":[0.1061779371],"iteration":589,"passed_time":7.00667536,"remaining_time":4.869045589},
{"learn":[0.1059098398],"iteration":590,"passed_time":7.019637333,"remaining_time":4.857921606},
{"learn":[0.1057085448],"iteration":591,"passed_time":7.028934786,"remaining_time":4.844265866},
{"learn":[0.1054261044],"iteration":592,"passed_time":7.043575007,"remaining_time":4.834291784},
{"learn":[0.1051998451],"iteration":593,"passed_time":7.059608363,"remaining_time":4.825254201},
{"learn":[0.1048615119],"iteration":594,"passed_time":7.075498914,"remaining_time":4.816095899},
{"learn":[0.1046297975],"iteration":595,"passed_time":7.089754537,"remaining_time":4.805806767},
{"learn":[0.1044899796],"iteration":596,"passed_time":7.101901749,"remaining_time":4.79408108},
{"learn":[0.1042394156],"iteration":597,"passed_time":7.123941159,"remaining_time":4.789003923},
{"learn":[0.1040977165],"iteration":598,"passed_time":7.137030805,"remaining_time":4.777878719},
{"learn":[0.1038129313],"iteration":599,"passed_time":7.148898573,"remaining_time":4.765932382},
{"learn":[0.1034958313],"iteration":600,"passed_time":7.163219648,"remaining_time":4.755615041},
{"learn":[0.103226263],"iteration":601,"passed_time":7.176460415,"remaining_time":4.744570175},
{"learn":[0.1030434699],"iteration":602,"passed_time":7.189720742,"remaining_time":4.733530903},
{"learn":[0.1027382769],"iteration":603,"passed_time":7.202464605,"remaining_time":4.722145668},
{"learn":[0.102500299],"iteration":604,"passed_time":7.215042392,"remaining_time":4.710647512},
{"learn":[0.102164816],"iteration":605,"passed_time":7.227627002,"remaining_time":4.699150229},
{"learn":[0.101927288],"iteration":606,"passed_time":7.241186601,"remaining_time":4.688280617},
{"learn":[0.1017937391],"iteration":607,"passed_time":7.254538706,"remaining_time":4.677268376},
{"learn":[0.1015078321],"iteration":608,"passed_time":7.26735516,"remaining_time":4.665904545},
{"learn":[0.1012285293],"iteration":609,"passed_time":7.280308798,"remaining_time":4.654623658},
{"learn":[0.101157402],"iteration":610,"passed_time":7.293277839,"remaining_time":4.643347102},
{"learn":[0.1009226305],"iteration":611,"passed_time":7.306474408,"remaining_time":4.632209265},
{"learn":[0.1007212014],"iteration":612,"passed_time":7.319107931,"remaining_time":4.620709248},
{"learn":[0.1004733573],"iteration":613,"passed_time":7.331574797,"remaining_time":4.609100768},
{"learn":[0.1003141951],"iteration":614,"passed_time":7.344888788,"remaining_time":4.59801981},
{"learn":[0.1001154889],"iteration":615,"passed_time":7.358020824,"remaining_time":4.586818176},
{"learn":[0.09991058914],"iteration":616,"passed_time":7.371032719,"remaining_time":4.575535708},
{"learn":[0.09965618115],"iteration":617,"passed_time":7.383934861,"remaining_time":4.564179801},
{"learn":[0.09944975438],"iteration":618,"passed_time":7.396980657,"remaining_time":4.552907319},
{"learn":[0.09918898854],"iteration":619,"passed_time":7.410641129,"remaining_time":4.542005853},
{"learn":[0.0989506303],"iteration":620,"passed_time":7.423886996,"remaining_time":4.530842466},
{"learn":[0.0986978728],"iteration":621,"passed_time":7.437541076,"remaining_time":4.519920461},
{"learn":[0.09854564302],"iteration":622,"passed_time":7.451348271,"remaining_time":4.509082341},
{"learn":[0.09836429231],"iteration":623,"passed_time":7.464836374,"remaining_time":4.49804243},
{"learn":[0.09825143945],"iteration":624,"passed_time":7.477637726,"remaining_time":4.486582636},
{"learn":[0.09807378815],"iteration":625,"passed_time":7.488826286,"remaining_time":4.474155002},
{"learn":[0.09783037214],"iteration":626,"passed_time":7.500821184,"remaining_time":4.462211007},
{"learn":[0.09770704192],"iteration":627,"passed_time":7.512844614,"remaining_time":4.450283752},
{"learn":[0.09744235518],"iteration":628,"passed_time":7.525218171,"remaining_time":4.438562705},
{"learn":[0.09716917923],"iteration":629,"passed_time":7.537510882,"remaining_time":4.426792105},
{"learn":[0.09686333754],"iteration":630,"passed_time":7.548284921,"remaining_time":4.414131753},
{"learn":[0.09664379962],"iteration":631,"passed_time":7.559752316,"remaining_time":4.401881095},
{"learn":[0.09645754266],"iteration":632,"passed_time":7.572074127,"remaining_time":4.390128285},
{"learn":[0.0962234265],"iteration":633,"passed_time":7.584355556,"remaining_time":4.378350368},
{"learn":[0.09600395901],"iteration":634,"passed_time":7.596835453,"remaining_time":4.366684946},
{"learn":[0.09567641283],"iteration":635,"passed_time":7.607626018,"remaining_time":4.354050111},
{"learn":[0.09554596624],"iteration":636,"passed_time":7.619245028,"remaining_time":4.341893164},
{"learn":[0.09535291079],"iteration":637,"passed_time":7.630199082,"remaining_time":4.329360608},
{"learn":[0.09517084528],"iteration":638,"passed_time":7.641553613,"remaining_time":4.31705924},
{"learn":[0.09498433492],"iteration":639,"passed_time":7.65363444,"remaining_time":4.305169372},
{"learn":[0.09477766571],"iteration":640,"passed_time":7.665821253,"remaining_time":4.293338268},
{"learn":[0.09459663845],"iteration":641,"passed_time":7.677472487,"remaining_time":4.281207399},
{"learn":[0.09442784102],"iteration":642,"passed_time":7.689179278,"remaining_time":4.269108868},
{"learn":[0.09429556032],"iteration":643,"passed_time":7.700958663,"remaining_time":4.257051683},
{"learn":[0.09412004357],"iteration":644,"passed_time":7.71363771,"remaining_time":4.245490522},
{"learn":[0.09390806565],"iteration":645,"passed_time":7.725258172,"remaining_time":4.23334581},
{"learn":[0.09362742616],"iteration":646,"passed_time":7.737235165,"remaining_time":4.221397239},
{"learn":[0.09345282016],"iteration":647,"passed_time":7.748237035,"remaining_time":4.208918883},
{"learn":[0.09335680852],"iteration":648,"passed_time":7.759748897,"remaining_time":4.196720898},
{"learn":[0.09308498476],"iteration":649,"passed_time":7.771380284,"remaining_time":4.184589384},
{"learn":[0.09292218394],"iteration":650,"passed_time":7.782572457,"remaining_time":4.172223944},
{"learn":[0.09264059555],"iteration":651,"passed_time":7.794488707,"remaining_time":4.160248574},
{"learn":[0.09251988794],"iteration":652,"passed_time":7.806045236,"remaining_time":4.148082231},
{"learn":[0.09236247599],"iteration":653,"passed_time":7.81693784,"remaining_time":4.135566502},
{"learn":[0.09215510333],"iteration":654,"passed_time":7.82872554,"remaining_time":4.123527193},
{"learn":[0.09191847191],"iteration":655,"passed_time":7.840430297,"remaining_time":4.111445156},
{"learn":[0.09175198158],"iteration":656,"passed_time":7.852061186,"remaining_time":4.099325703},
{"learn":[0.09151328211],"iteration":657,"passed_time":7.863422346,"remaining_time":4.087067541},
{"learn":[0.09131325135],"iteration":658,"passed_time":7.874811217,"remaining_time":4.074826442},
{"learn":[0.09103354996],"iteration":659,"passed_time":7.886172831,"remaining_time":4.062573883},
{"learn":[0.0909041329],"iteration":660,"passed_time":7.897492518,"remaining_time":4.050302517},
{"learn":[0.09072642994],"iteration":661,"passed_time":7.909342895,"remaining_time":4.038304982},
{"learn":[0.09052306035],"iteration":662,"passed_time":7.922074947,"remaining_time":4.026756044},
{"learn":[0.09037429884],"iteration":663,"passed_time":7.933241316,"remaining_time":4.014411269},
{"learn":[0.09014655916],"iteration":664,"passed_time":7.944754442,"remaining_time":4.002244719},
{"learn":[0.09003717865],"iteration":665,"passed_time":7.956739628,"remaining_time":3.990316871},
{"learn":[0.08995972616],"iteration":666,"passed_time":7.968714276,"remaining_time":3.978383589},
{"learn":[0.08975124857],"iteration":667,"passed_time":7.981378214,"remaining_time":3.966792765},
{"learn":[0.08956942924],"iteration":668,"passed_time":7.995009427,"remaining_time":3.95567731},
{"learn":[0.08939369948],"iteration":669,"passed_time":8.008964537,"remaining_time":3.944713876},
{"learn":[0.0891768997],"iteration":670,"passed_time":8.022139779,"remaining_time":3.933359147},
{"learn":[0.08904231939],"iteration":671,"passed_time":8.034881956,"remaining_time":3.921787621},
{"learn":[0.08890418837],"iteration":672,"passed_time":8.048495587,"remaining_time":3.910636043},
{"learn":[0.08867467998],"iteration":673,"passed_time":8.05995491,"remaining_time":3.898435164},
{"learn":[0.08849653965],"iteration":674,"passed_time":8.072089012,"remaining_time":3.886561376},
{"learn":[0.08835611286],"iteration":675,"passed_time":8.083451716,"remaining_time":3.874317095},
{"learn":[0.08818090263],"iteration":676,"passed_time":8.094677373,"remaining_time":3.862010032},
{"learn":[0.08799732365],"iteration":677,"passed_time":8.10749071,"remaining_time":3.85046019},
{"learn":[0.0878409341],"iteration":678,"passed_time":8.1223266,"remaining_time":3.839862796},
{"learn":[0.08771744697],"iteration":679,"passed_time":8.138707772,"remaining_time":3.829980128},
{"learn":[0.08752525354],"iteration":680,"passed_time":8.153706448,"remaining_time":3.819430774},
{"learn":[0.08733814599],"iteration":681,"passed_time":8.168177458,"remaining_time":3.808622334},
{"learn":[0.08725243128],"iteration":682,"passed_time":8.179970858,"remaining_time":3.796560413},
{"learn":[0.08710677305],"iteration":683,"passed_time":8.19158861,"remaining_time":3.78441813},
{"learn":[0.0868502578],"iteration":684,"passed_time":8.202505583,"remaining_time":3.771955122},
{"learn":[0.08668386068],"iteration":685,"passed_time":8.212859795,"remaining_time":3.759239031},
{"learn":[0.08648956636],"iteration":686,"passed_time":8.224495412,"remaining_time":3.74711363},
{"learn":[0.08635151538],"iteration":687,"passed_time":8.236268337,"remaining_time":3.73505192},
{"learn":[0.08626907072],"iteration":688,"passed_time":8.246083714,"remaining_time":3.722107453},
{"learn":[0.0861568025],"iteration":689,"passed_time":8.257262493,"remaining_time":3.709784598},
{"learn":[0.08597141255],"iteration":690,"passed_time":8.267757807,"remaining_time":3.697159425},
{"learn":[0.08576046954],"iteration":691,"passed_time":8.278359007,"remaining_time":3.684587535},
{"learn":[0.08559928831],"iteration":692,"passed_time":8.289824424,"remaining_time":3.672404182},
{"learn":[0.08538291284],"iteration":693,"passed_time":8.299652762,"remaining_time":3.659501074},
{"learn":[0.08520211854],"iteration":694,"passed_time":8.312020217,"remaining_time":3.647721102},
{"learn":[0.0850542466],"iteration":695,"passed_time":8.323559853,"remaining_time":3.635577867},
{"learn":[0.08494308942],"iteration":696,"passed_time":8.334392098,"remaining_time":3.623128846},
{"learn":[0.08474533054],"iteration":697,"passed_time":8.345534799,"remaining_time":3.610818781},
{"learn":[0.08449462582],"iteration":698,"passed_time":8.355937673,"remaining_time":3.598193476},
{"learn":[0.08436452396],"iteration":699,"passed_time":8.367888012,"remaining_time":3.586237719},
{"learn":[0.08416884381],"iteration":700,"passed_time":8.378767605,"remaining_time":3.573825269},
{"learn":[0.08400724831],"iteration":701,"passed_time":8.390287268,"remaining_time":3.561688897},
{"learn":[0.083722311],"iteration":702,"passed_time":8.402282586,"remaining_time":3.549755232},
{"learn":[0.08359902313],"iteration":703,"passed_time":8.412839474,"remaining_time":3.537216597},
{"learn":[0.08342616152],"iteration":704,"passed_time":8.424217012,"remaining_time":3.525026977},
{"learn":[0.08327710385],"iteration":705,"passed_time":8.434825194,"remaining_time":3.512519274},
{"learn":[0.08312227948],"iteration":706,"passed_time":8.447236233,"remaining_time":3.500764097},
{"learn":[0.08298411271],"iteration":707,"passed_time":8.458872252,"remaining_time":3.488687426},
{"learn":[0.08292113425],"iteration":708,"passed_time":8.469606782,"remaining_time":3.476241994},
{"learn":[0.08272821477],"iteration":709,"passed_time":8.481712734,"remaining_time":3.464361539},
{"learn":[0.08255732016],"iteration":710,"passed_time":8.492398884,"remaining_time":3.451903344},
{"learn":[0.08241973654],"iteration":711,"passed_time":8.503947344,"remaining_time":3.439798926},
{"learn":[0.08224665916],"iteration":712,"passed_time":8.516851297,"remaining_time":3.428241686},
{"learn":[0.08211757127],"iteration":713,"passed_time":8.528453067,"remaining_time":3.416159072},
{"learn":[0.08188468045],"iteration":714,"passed_time":8.538814543,"remaining_time":3.403583419},
{"learn":[0.08180688234],"iteration":715,"passed_time":8.549596317,"remaining_time":3.391180662},
{"learn":[0.08163711878],"iteration":716,"passed_time":8.560798374,"remaining_time":3.378948312},
{"learn":[0.08149978638],"iteration":717,"passed_time":8.572322115,"remaining_time":3.366845176},
{"learn":[0.08141193276],"iteration":718,"passed_time":8.58316081,"remaining_time":3.354475921},
{"learn":[0.08127255444],"iteration":719,"passed_time":8.594908232,"remaining_time":3.342464312},
{"learn":[0.08109111204],"iteration":720,"passed_time":8.604993892,"remaining_time":3.329810396},
{"learn":[0.08096446044],"iteration":721,"passed_time":8.615849649,"remaining_time":3.317460114},
{"learn":[0.08079582794],"iteration":722,"passed_time":8.628280833,"remaining_time":3.305717553},
{"learn":[0.08061966712],"iteration":723,"passed_time":8.640050829,"remaining_time":3.293721034},
{"learn":[0.08039540144],"iteration":724,"passed_time":8.649551113,"remaining_time":3.280864215},
{"learn":[0.08033579689],"iteration":725,"passed_time":8.660971636,"remaining_time":3.268741361},
{"learn":[0.08010048201],"iteration":726,"passed_time":8.671758219,"remaining_time":3.256382385},
{"learn":[0.07991267006],"iteration":727,"passed_time":8.682261539,"remaining_time":3.243921894},
{"learn":[0.07975380427],"iteration":728,"passed_time":8.693967041,"remaining_time":3.231913674},
{"learn":[0.07956939018],"iteration":729,"passed_time":8.705828347,"remaining_time":3.219963909},
{"learn":[0.07940650549],"iteration":730,"passed_time":8.718679077,"remaining_time":3.208378484},
{"learn":[0.07933900543],"iteration":731,"passed_time":8.731070319,"remaining_time":3.196621373},
{"learn":[0.07922610794],"iteration":732,"passed_time":8.743674695,"remaining_time":3.184940169},
{"learn":[0.07910243749],"iteration":733,"passed_time":8.75598893,"remaining_time":3.173151302},
{"learn":[0.07891750749],"iteration":734,"passed_time":8.768082427,"remaining_time":3.161281419},
{"learn":[0.07874410729],"iteration":735,"passed_time":8.777788811,"remaining_time":3.148554682},
{"learn":[0.07861213434],"iteration":736,"passed_time":8.787945715,"remaining_time":3.13599691},
{"learn":[0.07846151217],"iteration":737,"passed_time":8.798173549,"remaining_time":3.123470826},
{"learn":[0.07828459785],"iteration":738,"passed_time":8.811815394,"remaining_time":3.112156722},
{"learn":[0.07809091471],"iteration":739,"passed_time":8.824806812,"remaining_time":3.100607799},
{"learn":[0.07791337516],"iteration":740,"passed_time":8.837960537,"remaining_time":3.089111713},
{"learn":[0.07766211189],"iteration":741,"passed_time":8.85163848,"remaining_time":3.077793434},
{"learn":[0.07752028669],"iteration":742,"passed_time":8.861754568,"remaining_time":3.065236775},
{"learn":[0.07733080151],"iteration":743,"passed_time":8.872586282,"remaining_time":3.052932914},
{"learn":[0.0771736722],"iteration":744,"passed_time":8.883996783,"remaining_time":3.040831114},
{"learn":[0.0770653142],"iteration":745,"passed_time":8.894477635,"remaining_time":3.028414637},
{"learn":[0.07699271802],"iteration":746,"passed_time":8.905745328,"remaining_time":3.016269837},
{"learn":[0.07689314779],"iteration":747,"passed_time":8.916736474,"remaining_time":3.004034213},
{"learn":[0.0768285272],"iteration":748,"passed_time":8.926703328,"remaining_time":2.991458659},
{"learn":[0.07670828469],"iteration":749,"passed_time":8.93767277,"remaining_time":2.979224257},
{"learn":[0.07663882505],"iteration":750,"passed_time":8.948606916,"remaining_time":2.966981521},
{"learn":[0.07652586232],"iteration":751,"passed_time":8.959690033,"remaining_time":2.954791394},
{"learn":[0.07637974088],"iteration":752,"passed_time":8.970589551,"remaining_time":2.942543983},
{"learn":[0.07628168908],"iteration":753,"passed_time":8.982098024,"remaining_time":2.930498825},
{"learn":[0.07611773163],"iteration":754,"passed_time":8.99271608,"remaining_time":2.918166145},
{"learn":[0.07602093466],"iteration":755,"passed_time":9.002750983,"remaining_time":2.905649788},
{"learn":[0.07590219713],"iteration":756,"passed_time":9.01484438,"remaining_time":2.893800772},
{"learn":[0.07575233667],"iteration":757,"passed_time":9.026011646,"remaining_time":2.881655433},
{"learn":[0.07561595467],"iteration":758,"passed_time":9.037265951,"remaining_time":2.869540309},
{"learn":[0.07551947642],"iteration":759,"passed_time":9.049098411,"remaining_time":2.857610024},
{"learn":[0.07545119729],"iteration":760,"passed_time":9.060971052,"remaining_time":2.845692617},
{"learn":[0.07532567616],"iteration":761,"passed_time":9.071016286,"remaining_time":2.833204562},
{"learn":[0.0751921252],"iteration":762,"passed_time":9.083218446,"remaining_time":2.821392886},
{"learn":[0.07508170923],"iteration":763,"passed_time":9.094318491,"remaining_time":2.809239743},
{"learn":[0.07491613731],"iteration":764,"passed_time":9.106475433,"remaining_time":2.797414022},
{"learn":[0.07479627066],"iteration":765,"passed_time":9.116948252,"remaining_time":2.785072965},
{"learn":[0.07470563287],"iteration":766,"passed_time":9.127665199,"remaining_time":2.77281094},
{"learn":[0.07456491329],"iteration":767,"passed_time":9.137408549,"remaining_time":2.760258833},
{"learn":[0.07444181568],"iteration":768,"passed_time":9.148060026,"remaining_time":2.747986822},
{"learn":[0.07433275787],"iteration":769,"passed_time":9.15917264,"remaining_time":2.735856762},
{"learn":[0.07421944215],"iteration":770,"passed_time":9.168835569,"remaining_time":2.723298762},
{"learn":[0.07407967275],"iteration":771,"passed_time":9.179154104,"remaining_time":2.710941886},
{"learn":[0.07394727313],"iteration":772,"passed_time":9.189454954,"remaining_time":2.69858509},
{"learn":[0.07379775808],"iteration":773,"passed_time":9.200927447,"remaining_time":2.686575714},
{"learn":[0.07368259408],"iteration":774,"passed_time":9.211383497,"remaining_time":2.674272628},
{"learn":[0.07357022731],"iteration":775,"passed_time":9.223696783,"remaining_time":2.662510412},
{"learn":[0.07343235572],"iteration":776,"passed_time":9.234570277,"remaining_time":2.650333554},
{"learn":[0.073306543],"iteration":777,"passed_time":9.245044846,"remaining_time":2.638046216},
{"learn":[0.07318698432],"iteration":778,"passed_time":9.257264011,"remaining_time":2.626258468},
{"learn":[0.07299283668],"iteration":779,"passed_time":9.268927837,"remaining_time":2.61431298},
{"learn":[0.07287873587],"iteration":780,"passed_time":9.28118639,"remaining_time":2.60253498},
{"learn":[0.07273131725],"iteration":781,"passed_time":9.292488912,"remaining_time":2.590489236},
{"learn":[0.07262807055],"iteration":782,"passed_time":9.302923035,"remaining_time":2.578204724},
{"learn":[0.07257116558],"iteration":783,"passed_time":9.316615506,"remaining_time":2.566822639},
{"learn":[0.0725067311],"iteration":784,"passed_time":9.329283613,"remaining_time":2.555154111},
{"learn":[0.07231717563],"iteration":785,"passed_time":9.340283278,"remaining_time":2.543028781},
{"learn":[0.07222759402],"iteration":786,"passed_time":9.351036918,"remaining_time":2.530839725},
{"learn":[0.07208417117],"iteration":787,"passed_time":9.362178758,"remaining_time":2.518758752},
{"learn":[0.07194394852],"iteration":788,"passed_time":9.373288337,"remaining_time":2.506671533},
{"learn":[0.07179298303],"iteration":789,"passed_time":9.383764253,"remaining_time":2.494418346},
{"learn":[0.07169348638],"iteration":790,"passed_time":9.394824201,"remaining_time":2.482323967},
{"learn":[0.07160553629],"iteration":791,"passed_time":9.406837879,"remaining_time":2.470482675},
{"learn":[0.07149603345],"iteration":792,"passed_time":9.417535203,"remaining_time":2.458297335},
{"learn":[0.07137410448],"iteration":793,"passed_time":9.428249874,"remaining_time":2.446120244},
{"learn":[0.07126497457],"iteration":794,"passed_time":9.439250554,"remaining_time":2.434020583},
{"learn":[0.07119383714],"iteration":795,"passed_time":9.450970787,"remaining_time":2.422108091},
{"learn":[0.07100952176],"iteration":796,"passed_time":9.461617719,"remaining_time":2.409922706},
{"learn":[0.0708538091],"iteration":797,"passed_time":9.472418492,"remaining_time":2.397780119},
{"learn":[0.0707440604],"iteration":798,"passed_time":9.482933516,"remaining_time":2.385569007},
{"learn":[0.07066000665],"iteration":799,"passed_time":9.494775995,"remaining_time":2.373693999},
{"learn":[0.07058153632],"iteration":800,"passed_time":9.507903016,"remaining_time":2.362138203},
{"learn":[0.07047051168],"iteration":801,"passed_time":9.522623444,"remaining_time":2.350971873},
{"learn":[0.0702831781],"iteration":802,"passed_time":9.534786151,"remaining_time":2.339169205},
{"learn":[0.0702508276],"iteration":803,"passed_time":9.545290101,"remaining_time":2.326961268},
{"learn":[0.07014818412],"iteration":804,"passed_time":9.557395494,"remaining_time":2.315145492},
{"learn":[0.07001140135],"iteration":805,"passed_time":9.568354466,"remaining_time":2.30305306},
{"learn":[0.06983647263],"iteration":806,"passed_time":9.57912917,"remaining_time":2.290919368},
{"learn":[0.06975821954],"iteration":807,"passed_time":9.591668911,"remaining_time":2.279208454},
{"learn":[0.06970188314],"iteration":808,"passed_time":9.606992005,"remaining_time":2.268152624},
{"learn":[0.06959031572],"iteration":809,"passed_time":9.621815978,"remaining_time":2.25696918},
{"learn":[0.06946040083],"iteration":810,"passed_time":9.637898611,"remaining_time":2.246070083},
{"learn":[0.06931586779],"iteration":811,"passed_time":9.650709505,"remaining_time":2.234400723},
{"learn":[0.06923396767],"iteration":812,"passed_time":9.661679159,"remaining_time":2.222305046},
{"learn":[0.06920093804],"iteration":813,"passed_time":9.673342766,"remaining_time":2.210370706},
{"learn":[0.06913654225],"iteration":814,"passed_time":9.684003115,"remaining_time":2.198209296},
{"learn":[0.0689727406],"iteration":815,"passed_time":9.695643124,"remaining_time":2.186272469},
{"learn":[0.06884441281],"iteration":816,"passed_time":9.708057462,"remaining_time":2.174509811},
{"learn":[0.06870040724],"iteration":817,"passed_time":9.719396953,"remaining_time":2.162506413},
{"learn":[0.06860629851],"iteration":818,"passed_time":9.730996806,"remaining_time":2.150562176},
{"learn":[0.06848232891],"iteration":819,"passed_time":9.742201803,"remaining_time":2.138532103},
{"learn":[0.06839421056],"iteration":820,"passed_time":9.752744023,"remaining_time":2.126359537},
{"learn":[0.06824526056],"iteration":821,"passed_time":9.763898027,"remaining_time":2.114323417},
{"learn":[0.06814651399],"iteration":822,"passed_time":9.775317614,"remaining_time":2.102346559},
{"learn":[0.0680240303],"iteration":823,"passed_time":9.787122462,"remaining_time":2.090453341},
{"learn":[0.06795329794],"iteration":824,"passed_time":9.798469563,"remaining_time":2.078463241},
{"learn":[0.06785682627],"iteration":825,"passed_time":9.809641942,"remaining_time":2.066437891},
{"learn":[0.06771152828],"iteration":826,"passed_time":9.822813533,"remaining_time":2.054832819},
{"learn":[0.06753011324],"iteration":827,"passed_time":9.834016059,"remaining_time":2.04281493},
{"learn":[0.06734885743],"iteration":828,"passed_time":9.844362329,"remaining_time":2.030622386},
{"learn":[0.06724438619],"iteration":829,"passed_time":9.855529188,"remaining_time":2.018602364},
{"learn":[0.06711657041],"iteration":830,"passed_time":9.867531421,"remaining_time":2.006754284},
{"learn":[0.06702967142],"iteration":831,"passed_time":9.87995475,"remaining_time":1.994990863},
{"learn":[0.06693384435],"iteration":832,"passed_time":9.891446817,"remaining_time":1.983039158},
{"learn":[0.06684578999],"iteration":833,"passed_time":9.902339006,"remaining_time":1.970969155},
{"learn":[0.06674720999],"iteration":834,"passed_time":9.91508141,"remaining_time":1.959267584},
{"learn":[0.06663290917],"iteration":835,"passed_time":9.92633079,"remaining_time":1.947270633},
{"learn":[0.06653124157],"iteration":836,"passed_time":9.938090158,"remaining_time":1.935374786},
{"learn":[0.06644530832],"iteration":837,"passed_time":9.949545205,"remaining_time":1.923420433},
{"learn":[0.06637997922],"iteration":838,"passed_time":9.959822017,"remaining_time":1.911241174},
{"learn":[0.06624184397],"iteration":839,"passed_time":9.97106241,"remaining_time":1.899249983},
{"learn":[0.066164067],"iteration":840,"passed_time":9.983142941,"remaining_time":1.887419415},
{"learn":[0.06607921134],"iteration":841,"passed_time":9.993819026,"remaining_time":1.87532471},
{"learn":[0.0660101202],"iteration":842,"passed_time":10.0046318,"remaining_time":1.863258829},
{"learn":[0.06590462039],"iteration":843,"passed_time":10.01538958,"remaining_time":1.851185752},
{"learn":[0.06581167951],"iteration":844,"passed_time":10.02662796,"remaining_time":1.839203946},
{"learn":[0.06564863523],"iteration":845,"passed_time":10.03642128,"remaining_time":1.826960847},
{"learn":[0.06552548076],"iteration":846,"passed_time":10.04790401,"remaining_time":1.815028705},
{"learn":[0.06539025501],"iteration":847,"passed_time":10.05977586,"remaining_time":1.803167371},
{"learn":[0.06522339962],"iteration":848,"passed_time":10.07130486,"remaining_time":1.791245033},
{"learn":[0.06511100359],"iteration":849,"passed_time":10.08373153,"remaining_time":1.779482034},
{"learn":[0.06505489778],"iteration":850,"passed_time":10.09441778,"remaining_time":1.767412748},
{"learn":[0.06491193816],"iteration":851,"passed_time":10.10482746,"remaining_time":1.755298667},
{"learn":[0.06478406036],"iteration":852,"passed_time":10.1170479,"remaining_time":1.743500635},
{"learn":[0.06468828229],"iteration":853,"passed_time":10.13738371,"remaining_time":1.733089019},
{"learn":[0.06458880339],"iteration":854,"passed_time":10.15006234,"remaining_time":1.721355601},
{"learn":[0.06446217513],"iteration":855,"passed_time":10.1624637,"remaining_time":1.709573333},
{"learn":[0.06434957109],"iteration":856,"passed_time":10.17342579,"remaining_time":1.697549461},
{"learn":[0.06422510462],"iteration":857,"passed_time":10.18464921,"remaining_time":1.685571314},
{"learn":[0.06411022014],"iteration":858,"passed_time":10.19720827,"remaining_time":1.673814164},
{"learn":[0.06405121858],"iteration":859,"passed_time":10.20874335,"remaining_time":1.661888452},
{"learn":[0.06394595902],"iteration":860,"passed_time":10.2195244,"remaining_time":1.649841918},
{"learn":[0.06389488084],"iteration":861,"passed_time":10.23102807,"remaining_time":1.637914006},
{"learn":[0.06383634934],"iteration":862,"passed_time":10.24330365,"remaining_time":1.626109618},
{"learn":[0.06367898417],"iteration":863,"passed_time":10.25418802,"remaining_time":1.614085152},
{"learn":[0.06356023743],"iteration":864,"passed_time":10.26524202,"remaining_time":1.602089795},
{"learn":[0.06350833805],"iteration":865,"passed_time":10.27711181,"remaining_time":1.590222844},
{"learn":[0.06338810813],"iteration":866,"passed_time":10.2881273,"remaining_time":1.578224834},
{"learn":[0.06327297451],"iteration":867,"passed_time":10.29940442,"remaining_time":1.566268875},
{"learn":[0.0631763766],"iteration":868,"passed_time":10.31081904,"remaining_time":1.554335206},
{"learn":[0.06307313552],"iteration":869,"passed_time":10.32241382,"remaining_time":1.542429651},
{"learn":[0.06290780542],"iteration":870,"passed_time":10.33291724,"remaining_time":1.530363174},
{"learn":[0.06280223383],"iteration":871,"passed_time":10.34356284,"remaining_time":1.518321151},
{"learn":[0.06272202459],"iteration":872,"passed_time":10.3549691,"remaining_time":1.506392984},
{"learn":[0.06266929384],"iteration":873,"passed_time":10.36573733,"remaining_time":1.494374031},
{"learn":[0.06254564464],"iteration":874,"passed_time":10.3769231,"remaining_time":1.482417585},
{"learn":[0.06243560688],"iteration":875,"passed_time":10.38862933,"remaining_time":1.470536571},
{"learn":[0.06235245619],"iteration":876,"passed_time":10.4003936,"remaining_time":1.458664096},
{"learn":[0.06225488346],"iteration":877,"passed_time":10.41269041,"remaining_time":1.446865865},
{"learn":[0.06211622836],"iteration":878,"passed_time":10.42473066,"remaining_time":1.435031183},
{"learn":[0.0620240477],"iteration":879,"passed_time":10.43633431,"remaining_time":1.423136497},
{"learn":[0.06192061771],"iteration":880,"passed_time":10.44750007,"remaining_time":1.411183323},
{"learn":[0.06178218353],"iteration":881,"passed_time":10.45838735,"remaining_time":1.399194679},
{"learn":[0.06168660219],"iteration":882,"passed_time":10.47017691,"remaining_time":1.387328084},
{"learn":[0.06159435961],"iteration":883,"passed_time":10.48179203,"remaining_time":1.375438773},
{"learn":[0.06151518061],"iteration":884,"passed_time":10.49358622,"remaining_time":1.36357335},
{"learn":[0.06142898904],"iteration":885,"passed_time":10.50483735,"remaining_time":1.351638214},
{"learn":[0.06135221196],"iteration":886,"passed_time":10.51689545,"remaining_time":1.339807424},
{"learn":[0.0612777479],"iteration":887,"passed_time":10.52945868,"remaining_time":1.328039834},
{"learn":[0.06111570101],"iteration":888,"passed_time":10.54024491,"remaining_time":1.316048578},
{"learn":[0.06100255289],"iteration":889,"passed_time":10.55191104,"remaining_time":1.30416878},
{"learn":[0.06087753982],"iteration":890,"passed_time":10.56300395,"remaining_time":1.292219338},
{"learn":[0.06077293831],"iteration":891,"passed_time":10.57479872,"remaining_time":1.280356796},
{"learn":[0.06063760986],"iteration":892,"passed_time":10.58580725,"remaining_time":1.268400197},
{"learn":[0.06055609019],"iteration":893,"passed_time":10.59794316,"remaining_time":1.25657939},
{"learn":[0.06044160679],"iteration":894,"passed_time":10.60850933,"remaining_time":1.24457372},
{"learn":[0.06034588793],"iteration":895,"passed_time":10.61992254,"remaining_time":1.23266958},
{"learn":[0.0602403838],"iteration":896,"passed_time":10.63164648,"remaining_time":1.220802216},
{"learn":[0.0601705492],"iteration":897,"passed_time":10.6433986,"remaining_time":1.208938371},
{"learn":[0.06014259196],"iteration":898,"passed_time":10.65601707,"remaining_time":1.197172107},
{"learn":[0.06002870636],"iteration":899,"passed_time":10.66707554,"remaining_time":1.185230615},
{"learn":[0.05992642049],"iteration":900,"passed_time":10.67841768,"remaining_time":1.173322254},
{"learn":[0.05982470475],"iteration":901,"passed_time":10.69004585,"remaining_time":1.161446223},
{"learn":[0.05978246345],"iteration":902,"passed_time":10.70147986,"remaining_time":1.149549885},
{"learn":[0.05968331704],"iteration":903,"passed_time":10.71270507,"remaining_time":1.137632397},
{"learn":[0.05960135544],"iteration":904,"passed_time":10.72423596,"remaining_time":1.125748526},
{"learn":[0.05952985139],"iteration":905,"passed_time":10.73583017,"remaining_time":1.113872004},
{"learn":[0.05939329295],"iteration":906,"passed_time":10.74715656,"remaining_time":1.101968644},
{"learn":[0.05931196725],"iteration":907,"passed_time":10.75915838,"remaining_time":1.09013499},
{"learn":[0.0592278192],"iteration":908,"passed_time":10.77087042,"remaining_time":1.078271956},
{"learn":[0.05912890552],"iteration":909,"passed_time":10.78230068,"remaining_time":1.066381386},
{"learn":[0.05904379418],"iteration":910,"passed_time":10.7940464,"remaining_time":1.054522645},
{"learn":[0.05894358293],"iteration":911,"passed_time":10.80503512,"remaining_time":1.042591108},
{"learn":[0.05888437063],"iteration":912,"passed_time":10.81617983,"remaining_time":1.030676501},
{"learn":[0.05883130443],"iteration":913,"passed_time":10.82802019,"remaining_time":1.018829033},
{"learn":[0.05873790865],"iteration":914,"passed_time":10.83949205,"remaining_time":1.006947349},
{"learn":[0.05865386078],"iteration":915,"passed_time":10.85136937,"remaining_time":0.9951037417},
{"learn":[0.05859305087],"iteration":916,"passed_time":10.8638981,"remaining_time":0.9833190214},
{"learn":[0.05853629283],"iteration":917,"passed_time":10.87495229,"remaining_time":0.9714009671},
{"learn":[0.05842576577],"iteration":918,"passed_time":10.8868788,"remaining_time":0.959561679},
{"learn":[0.05831891167],"iteration":919,"passed_time":10.89861648,"remaining_time":0.9477057812},
{"learn":[0.05821652148],"iteration":920,"passed_time":10.91007122,"remaining_time":0.9358258698},
{"learn":[0.05814845036],"iteration":921,"passed_time":10.92087348,"remaining_time":0.9238916827},
{"learn":[0.05806363591],"iteration":922,"passed_time":10.93231476,"remaining_time":0.9120132572},
{"learn":[0.0579966285],"iteration":923,"passed_time":10.94381456,"remaining_time":0.9001405918},
{"learn":[0.0579103993],"iteration":924,"passed_time":10.95448029,"remaining_time":0.8882011048},
{"learn":[0.05782611724],"iteration":925,"passed_time":10.96622908,"remaining_time":0.8763509201},
{"learn":[0.05776753106],"iteration":926,"passed_time":10.97862184,"remaining_time":0.864551666},
{"learn":[0.05769511048],"iteration":927,"passed_time":10.99000252,"remaining_time":0.8526726095},
{"learn":[0.05762139597],"iteration":928,"passed_time":11.00207371,"remaining_time":0.8408473987},
{"learn":[0.0574886641],"iteration":929,"passed_time":11.0129938,"remaining_time":0.8289350169},
{"learn":[0.05733447977],"iteration":930,"passed_time":11.02452381,"remaining_time":0.817069971},
{"learn":[0.05725086669],"iteration":931,"passed_time":11.03703898,"remaining_time":0.8052775219},
{"learn":[0.05715509977],"iteration":932,"passed_time":11.04768478,"remaining_time":0.7933492821},
{"learn":[0.05707576169],"iteration":933,"passed_time":11.05934643,"remaining_time":0.781495572},
{"learn":[0.05697421681],"iteration":934,"passed_time":11.07070233,"remaining_time":0.7696210177},
{"learn":[0.05687425413],"iteration":935,"passed_time":11.08254144,"remaining_time":0.7577806115},
{"learn":[0.05678448092],"iteration":936,"passed_time":11.09377319,"remaining_time":0.7458993714},
{"learn":[0.05669925664],"iteration":937,"passed_time":11.10577112,"remaining_time":0.7340701593},
{"learn":[0.05656536437],"iteration":938,"passed_time":11.11792327,"remaining_time":0.7222506067},
{"learn":[0.05648838944],"iteration":939,"passed_time":11.1299213,"remaining_time":0.7104205086},
{"learn":[0.05637250757],"iteration":940,"passed_time":11.13990993,"remaining_time":0.6984640654},
{"learn":[0.05634032578],"iteration":941,"passed_time":11.15130963,"remaining_time":0.6865986819},
{"learn":[0.05621358571],"iteration":942,"passed_time":11.16205285,"remaining_time":0.674694605},
{"learn":[0.05616822674],"iteration":943,"passed_time":11.1737509,"remaining_time":0.6628496298},
{"learn":[0.05611542648],"iteration":944,"passed_time":11.1849552,"remaining_time":0.6509762287},
{"learn":[0.05601440645],"iteration":945,"passed_time":11.19647564,"remaining_time":0.6391222882},
{"learn":[0.05592672018],"iteration":946,"passed_time":11.20862362,"remaining_time":0.6273041729},
{"learn":[0.05581908849],"iteration":947,"passed_time":11.22067145,"remaining_time":0.6154798685},
{"learn":[0.05574818992],"iteration":948,"passed_time":11.23234341,"remaining_time":0.6036348937},
{"learn":[0.05566566126],"iteration":949,"passed_time":11.2446256,"remaining_time":0.5918224},
{"learn":[0.05557999774],"iteration":950,"passed_time":11.25618036,"remaining_time":0.579971438},
{"learn":[0.05547381238],"iteration":951,"passed_time":11.26799391,"remaining_time":0.5681341467},
{"learn":[0.05530945975],"iteration":952,"passed_time":11.27938418,"remaining_time":0.5562760298},
{"learn":[0.05524415074],"iteration":953,"passed_time":11.29125103,"remaining_time":0.5444418735},
{"learn":[0.05517378782],"iteration":954,"passed_time":11.3032963,"remaining_time":0.532616056},
{"learn":[0.05515474264],"iteration":955,"passed_time":11.3152905,"remaining_time":0.5207874289},
{"learn":[0.05505949579],"iteration":956,"passed_time":11.32745367,"remaining_time":0.5089660476},
{"learn":[0.05495659338],"iteration":957,"passed_time":11.33941643,"remaining_time":0.4971351669},
{"learn":[0.05491231141],"iteration":958,"passed_time":11.35153707,"remaining_time":0.4853107612},
{"learn":[0.05479090019],"iteration":959,"passed_time":11.36281074,"remaining_time":0.4734504475},
{"learn":[0.0546679496],"iteration":960,"passed_time":11.37516565,"remaining_time":0.4616352343},
{"learn":[0.05459978325],"iteration":961,"passed_time":11.38690955,"remaining_time":0.4497947641},
{"learn":[0.05448522581],"iteration":962,"passed_time":11.39942168,"remaining_time":0.4379840104},
{"learn":[0.05441103532],"iteration":963,"passed_time":11.41077584,"remaining_time":0.4261285584},
{"learn":[0.05428683387],"iteration":964,"passed_time":11.42133397,"remaining_time":0.4142452735},
{"learn":[0.05419564896],"iteration":965,"passed_time":11.43190437,"remaining_time":0.4023651641},
{"learn":[0.05414357187],"iteration":966,"passed_time":11.445345,"remaining_time":0.3905857134},
{"learn":[0.05405366159],"iteration":967,"passed_time":11.45685783,"remaining_time":0.3787391018},
{"learn":[0.05397126662],"iteration":968,"passed_time":11.46744585,"remaining_time":0.3668635927},
{"learn":[0.05385575408],"iteration":969,"passed_time":11.47876955,"remaining_time":0.3550134913},
{"learn":[0.0537534882],"iteration":970,"passed_time":11.48981714,"remaining_time":0.3431562277},
{"learn":[0.05366922712],"iteration":971,"passed_time":11.50189277,"remaining_time":0.3313302445},
{"learn":[0.0535688706],"iteration":972,"passed_time":11.51293798,"remaining_time":0.3194751547},
{"learn":[0.05350630123],"iteration":973,"passed_time":11.52550694,"remaining_time":0.307662403},
{"learn":[0.05343545557],"iteration":974,"passed_time":11.53649814,"remaining_time":0.2958076447},
{"learn":[0.05337471457],"iteration":975,"passed_time":11.54931927,"remaining_time":0.2839996542},
{"learn":[0.05328060498],"iteration":976,"passed_time":11.55959195,"remaining_time":0.2721295956},
{"learn":[0.05325504449],"iteration":977,"passed_time":11.57146577,"remaining_time":0.260298821},
{"learn":[0.05318718384],"iteration":978,"passed_time":11.58289133,"remaining_time":0.2484583432},
{"learn":[0.05313881553],"iteration":979,"passed_time":11.5954016,"remaining_time":0.236640849},
{"learn":[0.05307973442],"iteration":980,"passed_time":11.60669308,"remaining_time":0.2247983369},
{"learn":[0.05300582564],"iteration":981,"passed_time":11.61662647,"remaining_time":0.2129320534},
{"learn":[0.05292172839],"iteration":982,"passed_time":11.62676366,"remaining_time":0.2010732271},
{"learn":[0.05285042971],"iteration":983,"passed_time":11.63867728,"remaining_time":0.1892467851},
{"learn":[0.05278122603],"iteration":984,"passed_time":11.65036028,"remaining_time":0.1774166541},
{"learn":[0.05271924705],"iteration":985,"passed_time":11.66161592,"remaining_time":0.1655807534},
{"learn":[0.05265314685],"iteration":986,"passed_time":11.67442911,"remaining_time":0.1537665436},
{"learn":[0.0525858178],"iteration":987,"passed_time":11.68587189,"remaining_time":0.1419336667},
{"learn":[0.05251077573],"iteration":988,"passed_time":11.69736615,"remaining_time":0.1301021513},
{"learn":[0.05244066722],"iteration":989,"passed_time":11.70821912,"remaining_time":0.1182648396},
{"learn":[0.0523757281],"iteration":990,"passed_time":11.71983793,"remaining_time":0.1064364696},
{"learn":[0.05229746888],"iteration":991,"passed_time":11.73083007,"remaining_time":0.09460346834},
{"learn":[0.05224191781],"iteration":992,"passed_time":11.74314722,"remaining_time":0.08278150108},
{"learn":[0.05218588337],"iteration":993,"passed_time":11.75439977,"remaining_time":0.0709521113},
{"learn":[0.05212749711],"iteration":994,"passed_time":11.76537715,"remaining_time":0.05912249824},
{"learn":[0.05209930306],"iteration":995,"passed_time":11.7765924,"remaining_time":0.04729555182},
{"learn":[0.05197988424],"iteration":996,"passed_time":11.78714932,"remaining_time":0.03546785151},
{"learn":[0.0518802498],"iteration":997,"passed_time":11.79821624,"remaining_time":0.02364371992},
{"learn":[0.05181130726],"iteration":998,"passed_time":11.80868243,"remaining_time":0.01182050294},
{"learn":[0.05170946406],"iteration":999,"passed_time":11.81924448,"remaining_time":0}
]}